{
  "metadata": {
    "generated_at": "2026-06-28 19:43:08",
    "version": "v200",
    "location": "Bandara_Sangia_Ni_Bandera"
  },
  "data": [
    {
      "Datetime": "2026-06-28 15:00:00",
      "Temperature": 29.6,
      "Dewpoint": 21.6,
      "Pressure": 1008.4,
      "Rain": 0.0,
      "Wind": 0.5,
      "Wind Dir.": 62.0,
      "Wind Gust": 3.8,
      "Prob Precip 0.1mm": 67.1,
      "Prob Precip 1.0mm": 40.5,
      "Prob Precip 10.0mm": 0.0,
      "Sunshine": 46.0,
      "Low Clouds": 24.0,
      "Mid Clouds": 28.0,
      "High Clouds": 0.0,
      "Condition": "Normal"
    },
    {
      "Datetime": "2026-06-28 16:00:00",
      "Temperature": 29.300000000000004,
      "Dewpoint": 22.2,
      "Pressure": 1008.6,
      "Rain": 0.3,
      "Wind": 3.2,
      "Wind Dir.": 46.0,
      "Wind Gust": 5.4,
      "Prob Precip 0.1mm": 61.3,
      "Prob Precip 1.0mm": 39.3,
      "Prob Precip 10.0mm": 0.0,
      "Sunshine": 40.0,
      "Low Clouds": 28.999999999999996,
      "Mid Clouds": 34.0,
      "High Clouds": 0.0,
      "Condition": "Light Rain"
    },
    {
      "Datetime": "2026-06-28 17:00:00",
      "Temperature": 28.7,
      "Dewpoint": 23.1,
      "Pressure": 1009.0999999999999,
      "Rain": 0.2,
      "Wind": 4.3,
      "Wind Dir.": 55.0,
      "Wind Gust": 7.0,
      "Prob Precip 0.1mm": 55.5,
      "Prob Precip 1.0mm": 38.1,
      "Prob Precip 10.0mm": 0.0,
      "Sunshine": 43.0,
      "Low Clouds": 18.0,
      "Mid Clouds": 20.0,
      "High Clouds": 0.0,
      "Condition": "Light Rain"
    },
    {
      "Datetime": "2026-06-28 18:00:00",
      "Temperature": 28.2,
      "Dewpoint": 23.7,
      "Pressure": 1009.4,
      "Rain": 0.0,
      "Wind": 4.3,
      "Wind Dir.": 79.0,
      "Wind Gust": 6.5,
      "Prob Precip 0.1mm": 41.9,
      "Prob Precip 1.0mm": 25.4,
      "Prob Precip 10.0mm": 0.0,
      "Sunshine": 40.0,
      "Low Clouds": 21.0,
      "Mid Clouds": 13.0,
      "High Clouds": 0.0,
      "Condition": "Normal"
    },
    {
      "Datetime": "2026-06-28 19:00:00",
      "Temperature": 27.8,
      "Dewpoint": 23.4,
      "Pressure": 1010.0,
      "Rain": 0.0,
      "Wind": 4.9,
      "Wind Dir.": 97.0,
      "Wind Gust": 7.6,
      "Prob Precip 0.1mm": 28.3,
      "Prob Precip 1.0mm": 12.7,
      "Prob Precip 10.0mm": 0.0,
      "Sunshine": 0.0,
      "Low Clouds": 23.0,
      "Mid Clouds": 26.0,
      "High Clouds": 0.0,
      "Condition": "Normal"
    },
    {
      "Datetime": "2026-06-28 20:00:00",
      "Temperature": 27.4,
      "Dewpoint": 22.9,
      "Pressure": 1010.5000000000001,
      "Rain": 0.2,
      "Wind": 7.6,
      "Wind Dir.": 107.0,
      "Wind Gust": 10.8,
      "Prob Precip 0.1mm": 14.699999999999998,
      "Prob Precip 1.0mm": 0.0,
      "Prob Precip 10.0mm": 0.0,
      "Sunshine": 0.0,
      "Low Clouds": 14.0,
      "Mid Clouds": 23.0,
      "High Clouds": 0.0,
      "Condition": "Light Rain"
    },
    {
      "Datetime": "2026-06-28 21:00:00",
      "Temperature": 26.8,
      "Dewpoint": 23.2,
      "Pressure": 1011.0,
      "Rain": 0.0,
      "Wind": 7.6,
      "Wind Dir.": 113.0,
      "Wind Gust": 10.8,
      "Prob Precip 0.1mm": 9.8,
      "Prob Precip 1.0mm": 0.0,
      "Prob Precip 10.0mm": 0.0,
      "Sunshine": 0.0,
      "Low Clouds": 10.0,
      "Mid Clouds": 16.0,
      "High Clouds": 0.0,
      "Condition": "Normal"
    },
    {
      "Datetime": "2026-06-28 22:00:00",
      "Temperature": 26.6,
      "Dewpoint": 23.1,
      "Pressure": 1011.2,
      "Rain": 0.0,
      "Wind": 5.9,
      "Wind Dir.": 112.0,
      "Wind Gust": 9.2,
      "Prob Precip 0.1mm": 4.9,
      "Prob Precip 1.0mm": 0.0,
      "Prob Precip 10.0mm": 0.0,
      "Sunshine": 0.0,
      "Low Clouds": 15.0,
      "Mid Clouds": 10.0,
      "High Clouds": 0.0,
      "Condition": "Normal"
    },
    {
      "Datetime": "2026-06-28 23:00:00",
      "Temperature": 26.5,
      "Dewpoint": 23.0,
      "Pressure": 1011.3999999999999,
      "Rain": 0.0,
      "Wind": 5.4,
      "Wind Dir.": 104.0,
      "Wind Gust": 8.6,
      "Prob Precip 0.1mm": 0.0,
      "Prob Precip 1.0mm": 0.0,
      "Prob Precip 10.0mm": 0.0,
      "Sunshine": 0.0,
      "Low Clouds": 17.0,
      "Mid Clouds": 9.0,
      "High Clouds": 0.0,
      "Condition": "Normal"
    },
    {
      "Datetime": "2026-06-29 00:00:00",
      "Temperature": 26.3,
      "Dewpoint": 22.9,
      "Pressure": 1011.5,
      "Rain": 0.0,
      "Wind": 4.9,
      "Wind Dir.": 96.00000000000001,
      "Wind Gust": 8.1,
      "Prob Precip 0.1mm": 0.2,
      "Prob Precip 1.0mm": 0.0,
      "Prob Precip 10.0mm": 0.0,
      "Sunshine": 0.0,
      "Low Clouds": 18.0,
      "Mid Clouds": 17.0,
      "High Clouds": 0.0,
      "Condition": "Normal"
    },
    {
      "Datetime": "2026-06-29 01:00:00",
      "Temperature": 26.1,
      "Dewpoint": 22.9,
      "Pressure": 1011.1000000000001,
      "Rain": 0.0,
      "Wind": 4.9,
      "Wind Dir.": 97.0,
      "Wind Gust": 8.1,
      "Prob Precip 0.1mm": 0.5,
      "Prob Precip 1.0mm": 0.0,
      "Prob Precip 10.0mm": 0.0,
      "Sunshine": 0.0,
      "Low Clouds": 15.0,
      "Mid Clouds": 35.0,
      "High Clouds": 0.0,
      "Condition": "Normal"
    },
    {
      "Datetime": "2026-06-29 02:00:00",
      "Temperature": 25.833333333333336,
      "Dewpoint": 22.400000000000002,
      "Pressure": 1010.5666666666666,
      "Rain": 0.0,
      "Wind": 5.2,
      "Wind Dir.": 101.66500913598081,
      "Wind Gust": 8.833333333333332,
      "Prob Precip 0.1mm": 0.23333333333333334,
      "Prob Precip 1.0mm": 0.0,
      "Prob Precip 10.0mm": 0.0,
      "Sunshine": 0.0,
      "Low Clouds": 24.333333333333332,
      "Mid Clouds": 18.666666666666664,
      "High Clouds": 0.0,
      "Condition": "Normal"
    },
    {
      "Datetime": "2026-06-29 03:00:00",
      "Temperature": 25.85,
      "Dewpoint": 22.349999999999998,
      "Pressure": 1010.35,
      "Rain": 0.0,
      "Wind": 4.050000000000001,
      "Wind Dir.": 85.5,
      "Wind Gust": 7.55,
      "Prob Precip 0.1mm": 0.5,
      "Prob Precip 1.0mm": 0.0,
      "Prob Precip 10.0mm": 0.0,
      "Sunshine": 0.0,
      "Low Clouds": 38.00000000000001,
      "Mid Clouds": 27.000000000000004,
      "High Clouds": 0.0,
      "Condition": "Normal"
    },
    {
      "Datetime": "2026-06-29 04:00:00",
      "Temperature": 24.160000000000007,
      "Dewpoint": 21.720000000000002,
      "Pressure": 1010.6400000000001,
      "Rain": 0.0,
      "Wind": 4.880000000000001,
      "Wind Dir.": 80.81589881182201,
      "Wind Gust": 8.52,
      "Prob Precip 0.1mm": 0.26000000000000006,
      "Prob Precip 1.0mm": 0.0,
      "Prob Precip 10.0mm": 0.0,
      "Sunshine": 0.0,
      "Low Clouds": 17.6,
      "Mid Clouds": 10.8,
      "High Clouds": 0.0,
      "Condition": "Normal"
    },
    {
      "Datetime": "2026-06-29 05:00:00",
      "Temperature": 24.47142857142858,
      "Dewpoint": 21.78571428571429,
      "Pressure": 1010.8428571428572,
      "Rain": 0.0,
      "Wind": 5.4142857142857155,
      "Wind Dir.": 84.47016848357393,
      "Wind Gust": 8.928571428571429,
      "Prob Precip 0.1mm": 0.22857142857142862,
      "Prob Precip 1.0mm": 0.0,
      "Prob Precip 10.0mm": 0.0,
      "Sunshine": 0.0,
      "Low Clouds": 15.000000000000004,
      "Mid Clouds": 7.714285714285715,
      "High Clouds": 0.0,
      "Condition": "Normal"
    },
    {
      "Datetime": "2026-06-29 06:00:00",
      "Temperature": 23.919999999999998,
      "Dewpoint": 21.560000000000002,
      "Pressure": 1011.3200000000002,
      "Rain": 0.0,
      "Wind": 4.640000000000001,
      "Wind Dir.": 87.4085056887718,
      "Wind Gust": 7.900000000000001,
      "Prob Precip 0.1mm": 0.2,
      "Prob Precip 1.0mm": 0.0,
      "Prob Precip 10.0mm": 0.0,
      "Sunshine": 0.0,
      "Low Clouds": 11.6,
      "Mid Clouds": 11.000000000000002,
      "High Clouds": 0.0,
      "Condition": "Normal"
    },
    {
      "Datetime": "2026-06-29 07:00:00",
      "Temperature": 24.420000000000005,
      "Dewpoint": 21.720000000000002,
      "Pressure": 1011.8600000000001,
      "Rain": 0.0,
      "Wind": 4.78,
      "Wind Dir.": 102.84997393163928,
      "Wind Gust": 8.3,
      "Prob Precip 0.1mm": 0.1,
      "Prob Precip 1.0mm": 0.0,
      "Prob Precip 10.0mm": 0.0,
      "Sunshine": 24.8,
      "Low Clouds": 10.6,
      "Mid Clouds": 12.600000000000001,
      "High Clouds": 0.0,
      "Condition": "Normal"
    },
    {
      "Datetime": "2026-06-29 08:00:00",
      "Temperature": 26.157142857142862,
      "Dewpoint": 21.800000000000004,
      "Pressure": 1012.2428571428574,
      "Rain": 0.0,
      "Wind": 5.714285714285715,
      "Wind Dir.": 99.10035336823131,
      "Wind Gust": 10.485714285714288,
      "Prob Precip 0.1mm": 0.0,
      "Prob Precip 1.0mm": 0.0,
      "Prob Precip 10.0mm": 0.0,
      "Sunshine": 23.42857142857143,
      "Low Clouds": 6.714285714285715,
      "Mid Clouds": 9.428571428571429,
      "High Clouds": 0.0,
      "Condition": "Normal"
    },
    {
      "Datetime": "2026-06-29 09:00:00",
      "Temperature": 27.259999999999998,
      "Dewpoint": 21.48,
      "Pressure": 1012.28,
      "Rain": 0.0,
      "Wind": 6.26,
      "Wind Dir.": 98.59137474370094,
      "Wind Gust": 11.879999999999999,
      "Prob Precip 0.1mm": 9.64,
      "Prob Precip 1.0mm": 0.0,
      "Prob Precip 10.0mm": 0.0,
      "Sunshine": 27.200000000000006,
      "Low Clouds": 13.400000000000002,
      "Mid Clouds": 13.200000000000003,
      "High Clouds": 0.0,
      "Condition": "Normal"
    },
    {
      "Datetime": "2026-06-29 10:00:00",
      "Temperature": 28.360000000000003,
      "Dewpoint": 21.28,
      "Pressure": 1011.8800000000002,
      "Rain": 0.0,
      "Wind": 5.520000000000001,
      "Wind Dir.": 94.70605202022142,
      "Wind Gust": 11.46,
      "Prob Precip 0.1mm": 19.220000000000002,
      "Prob Precip 1.0mm": 0.0,
      "Prob Precip 10.0mm": 0.0,
      "Sunshine": 27.000000000000004,
      "Low Clouds": 17.400000000000002,
      "Mid Clouds": 14.2,
      "High Clouds": 0.0,
      "Condition": "Normal"
    },
    {
      "Datetime": "2026-06-29 11:00:00",
      "Temperature": 29.27142857142858,
      "Dewpoint": 21.1,
      "Pressure": 1011.1571428571431,
      "Rain": 0.04285714285714286,
      "Wind": 4.242857142857144,
      "Wind Dir.": 100.09851114552848,
      "Wind Gust": 9.957142857142857,
      "Prob Precip 0.1mm": 28.3,
      "Prob Precip 1.0mm": 0.0,
      "Prob Precip 10.0mm": 0.0,
      "Sunshine": 25.714285714285722,
      "Low Clouds": 13.571428571428575,
      "Mid Clouds": 10.571428571428573,
      "High Clouds": 0.0,
      "Condition": "Normal"
    },
    {
      "Datetime": "2026-06-29 12:00:00",
      "Temperature": 29.7,
      "Dewpoint": 20.900000000000002,
      "Pressure": 1010.4200000000001,
      "Rain": 0.06000000000000001,
      "Wind": 4.86,
      "Wind Dir.": 136.46107403322912,
      "Wind Gust": 10.92,
      "Prob Precip 0.1mm": 31.22,
      "Prob Precip 1.0mm": 6.9,
      "Prob Precip 10.0mm": 0.0,
      "Sunshine": 25.0,
      "Low Clouds": 21.800000000000004,
      "Mid Clouds": 17.200000000000003,
      "High Clouds": 0.0,
      "Condition": "Normal"
    },
    {
      "Datetime": "2026-06-29 13:00:00",
      "Temperature": 30.040000000000003,
      "Dewpoint": 20.86,
      "Pressure": 1009.6000000000001,
      "Rain": 0.0,
      "Wind": 5.5200000000000005,
      "Wind Dir.": 134.46947475538363,
      "Wind Gust": 10.28,
      "Prob Precip 0.1mm": 33.580000000000005,
      "Prob Precip 1.0mm": 13.82,
      "Prob Precip 10.0mm": 0.0,
      "Sunshine": 21.400000000000002,
      "Low Clouds": 36.800000000000004,
      "Mid Clouds": 19.0,
      "High Clouds": 0.0,
      "Condition": "Normal"
    },
    {
      "Datetime": "2026-06-29 14:00:00",
      "Temperature": 29.928571428571438,
      "Dewpoint": 21.171428571428574,
      "Pressure": 1008.8714285714287,
      "Rain": 0.018571428571428576,
      "Wind": 5.92857142857143,
      "Wind Dir.": 167.20388148067016,
      "Wind Gust": 10.185714285714285,
      "Prob Precip 0.1mm": 34.728571428571435,
      "Prob Precip 1.0mm": 19.85714285714286,
      "Prob Precip 10.0mm": 0.0,
      "Sunshine": 17.571428571428573,
      "Low Clouds": 33.00000000000001,
      "Mid Clouds": 13.142857142857144,
      "High Clouds": 0.0,
      "Condition": "Normal"
    },
    {
      "Datetime": "2026-06-29 15:00:00",
      "Temperature": 29.66,
      "Dewpoint": 21.199999999999996,
      "Pressure": 1008.44,
      "Rain": 0.02,
      "Wind": 5.720000000000001,
      "Wind Dir.": 139.82322786668865,
      "Wind Gust": 10.28,
      "Prob Precip 0.1mm": 45.42000000000001,
      "Prob Precip 1.0mm": 18.88,
      "Prob Precip 10.0mm": 0.0,
      "Sunshine": 13.8,
      "Low Clouds": 55.400000000000006,
      "Mid Clouds": 16.400000000000002,
      "High Clouds": 0.0,
      "Condition": "Normal"
    },
    {
      "Datetime": "2026-06-29 16:00:00",
      "Temperature": 29.500000000000007,
      "Dewpoint": 21.240000000000002,
      "Pressure": 1008.3199999999999,
      "Rain": 0.02,
      "Wind": 4.32,
      "Wind Dir.": 133.54122762442336,
      "Wind Gust": 8.540000000000001,
      "Prob Precip 0.1mm": 54.88000000000001,
      "Prob Precip 1.0mm": 17.12,
      "Prob Precip 10.0mm": 0.0,
      "Sunshine": 12.000000000000002,
      "Low Clouds": 41.60000000000001,
      "Mid Clouds": 16.2,
      "High Clouds": 0.0,
      "Condition": "Normal"
    },
    {
      "Datetime": "2026-06-29 17:00:00",
      "Temperature": 28.75714285714286,
      "Dewpoint": 21.814285714285717,
      "Pressure": 1008.6428571428572,
      "Rain": 0.042857142857142864,
      "Wind": 4.114285714285715,
      "Wind Dir.": 87.97880092627368,
      "Wind Gust": 8.8,
      "Prob Precip 0.1mm": 63.60000000000002,
      "Prob Precip 1.0mm": 14.542857142857144,
      "Prob Precip 10.0mm": 0.0,
      "Sunshine": 9.142857142857144,
      "Low Clouds": 39.00000000000001,
      "Mid Clouds": 17.85714285714286,
      "High Clouds": 0.0,
      "Condition": "Normal"
    },
    {
      "Datetime": "2026-06-29 18:00:00",
      "Temperature": 27.72000000000001,
      "Dewpoint": 21.360000000000003,
      "Pressure": 1009.1199999999999,
      "Rain": 0.0,
      "Wind": 5.4,
      "Wind Dir.": 80.80435038411925,
      "Wind Gust": 10.060000000000002,
      "Prob Precip 0.1mm": 55.320000000000014,
      "Prob Precip 1.0mm": 10.220000000000002,
      "Prob Precip 10.0mm": 0.0,
      "Sunshine": 2.8000000000000003,
      "Low Clouds": 50.2,
      "Mid Clouds": 25.200000000000003,
      "High Clouds": 0.0,
      "Condition": "Normal"
    },
    {
      "Datetime": "2026-06-29 19:00:00",
      "Temperature": 26.820000000000004,
      "Dewpoint": 21.68,
      "Pressure": 1009.7999999999998,
      "Rain": 0.0,
      "Wind": 5.94,
      "Wind Dir.": 82.96754539963598,
      "Wind Gust": 9.940000000000001,
      "Prob Precip 0.1mm": 46.220000000000006,
      "Prob Precip 1.0mm": 5.0600000000000005,
      "Prob Precip 10.0mm": 0.0,
      "Sunshine": 0.0,
      "Low Clouds": 32.2,
      "Mid Clouds": 16.8,
      "High Clouds": 0.0,
      "Condition": "Normal"
    },
    {
      "Datetime": "2026-06-29 20:00:00",
      "Temperature": 26.55714285714286,
      "Dewpoint": 21.928571428571434,
      "Pressure": 1010.457142857143,
      "Rain": 0.004285714285714286,
      "Wind": 5.7857142857142865,
      "Wind Dir.": 96.10030659568889,
      "Wind Gust": 10.042857142857144,
      "Prob Precip 0.1mm": 36.87142857142858,
      "Prob Precip 1.0mm": 0.0,
      "Prob Precip 10.0mm": 0.0,
      "Sunshine": 1.5714285714285718,
      "Low Clouds": 11.571428571428573,
      "Mid Clouds": 6.571428571428573,
      "High Clouds": 0.0,
      "Condition": "Normal"
    },
    {
      "Datetime": "2026-06-29 21:00:00",
      "Temperature": 25.720000000000002,
      "Dewpoint": 21.660000000000004,
      "Pressure": 1011.04,
      "Rain": 0.0,
      "Wind": 7.0200000000000005,
      "Wind Dir.": 92.97024298244082,
      "Wind Gust": 12.100000000000001,
      "Prob Precip 0.1mm": 26.0,
      "Prob Precip 1.0mm": 0.0,
      "Prob Precip 10.0mm": 0.0,
      "Sunshine": 0.0,
      "Low Clouds": 17.4,
      "Mid Clouds": 5.0,
      "High Clouds": 0.0,
      "Condition": "Normal"
    },
    {
      "Datetime": "2026-06-29 22:00:00",
      "Temperature": 25.280000000000005,
      "Dewpoint": 21.580000000000002,
      "Pressure": 1011.08,
      "Rain": 0.0,
      "Wind": 6.78,
      "Wind Dir.": 94.39060279847047,
      "Wind Gust": 11.98,
      "Prob Precip 0.1mm": 14.920000000000002,
      "Prob Precip 1.0mm": 0.0,
      "Prob Precip 10.0mm": 0.0,
      "Sunshine": 0.0,
      "Low Clouds": 10.0,
      "Mid Clouds": 1.0,
      "High Clouds": 0.0,
      "Condition": "Normal"
    },
    {
      "Datetime": "2026-06-29 23:00:00",
      "Temperature": 25.285714285714292,
      "Dewpoint": 21.800000000000004,
      "Pressure": 1011.057142857143,
      "Rain": 0.0,
      "Wind": 6.457142857142859,
      "Wind Dir.": 92.57691922324376,
      "Wind Gust": 10.4,
      "Prob Precip 0.1mm": 3.585714285714286,
      "Prob Precip 1.0mm": 0.0,
      "Prob Precip 10.0mm": 0.0,
      "Sunshine": 0.0,
      "Low Clouds": 7.571428571428573,
      "Mid Clouds": 1.7142857142857146,
      "High Clouds": 0.0,
      "Condition": "Normal"
    },
    {
      "Datetime": "2026-06-30 00:00:00",
      "Temperature": 24.580000000000002,
      "Dewpoint": 21.540000000000003,
      "Pressure": 1010.9400000000002,
      "Rain": 0.0,
      "Wind": 6.36,
      "Wind Dir.": 98.03098574753213,
      "Wind Gust": 10.680000000000001,
      "Prob Precip 0.1mm": 2.72,
      "Prob Precip 1.0mm": 0.0,
      "Prob Precip 10.0mm": 0.0,
      "Sunshine": 0.0,
      "Low Clouds": 15.600000000000001,
      "Mid Clouds": 7.800000000000001,
      "High Clouds": 0.0,
      "Condition": "Normal"
    },
    {
      "Datetime": "2026-06-30 01:00:00",
      "Temperature": 24.360000000000003,
      "Dewpoint": 21.5,
      "Pressure": 1010.4800000000001,
      "Rain": 0.0,
      "Wind": 6.48,
      "Wind Dir.": 97.83340954461787,
      "Wind Gust": 10.6,
      "Prob Precip 0.1mm": 1.5999999999999999,
      "Prob Precip 1.0mm": 0.0,
      "Prob Precip 10.0mm": 0.0,
      "Sunshine": 0.0,
      "Low Clouds": 9.600000000000001,
      "Mid Clouds": 9.8,
      "High Clouds": 0.0,
      "Condition": "Normal"
    },
    {
      "Datetime": "2026-06-30 02:00:00",
      "Temperature": 24.557142857142864,
      "Dewpoint": 21.542857142857148,
      "Pressure": 1010.1285714285716,
      "Rain": 0.0,
      "Wind": 6.714285714285715,
      "Wind Dir.": 99.32820159867099,
      "Wind Gust": 10.185714285714287,
      "Prob Precip 0.1mm": 0.34285714285714286,
      "Prob Precip 1.0mm": 0.0,
      "Prob Precip 10.0mm": 0.0,
      "Sunshine": 0.0,
      "Low Clouds": 7.000000000000001,
      "Mid Clouds": 9.285714285714286,
      "High Clouds": 0.0,
      "Condition": "Normal"
    },
    {
      "Datetime": "2026-06-30 03:00:00",
      "Temperature": 23.940000000000005,
      "Dewpoint": 21.419999999999998,
      "Pressure": 1010.0800000000002,
      "Rain": 0.0,
      "Wind": 6.160000000000001,
      "Wind Dir.": 97.65088886999054,
      "Wind Gust": 10.38,
      "Prob Precip 0.1mm": 0.32,
      "Prob Precip 1.0mm": 0.0,
      "Prob Precip 10.0mm": 0.0,
      "Sunshine": 0.0,
      "Low Clouds": 11.6,
      "Mid Clouds": 13.600000000000001,
      "High Clouds": 0.0,
      "Condition": "Normal"
    },
    {
      "Datetime": "2026-06-30 04:00:00",
      "Temperature": 23.840000000000003,
      "Dewpoint": 21.380000000000003,
      "Pressure": 1010.2200000000001,
      "Rain": 0.0,
      "Wind": 6.0600000000000005,
      "Wind Dir.": 95.01069463664695,
      "Wind Gust": 10.280000000000001,
      "Prob Precip 0.1mm": 0.16,
      "Prob Precip 1.0mm": 0.0,
      "Prob Precip 10.0mm": 0.0,
      "Sunshine": 0.0,
      "Low Clouds": 12.600000000000001,
      "Mid Clouds": 13.400000000000002,
      "High Clouds": 0.0,
      "Condition": "Normal"
    },
    {
      "Datetime": "2026-06-30 05:00:00",
      "Temperature": 24.228571428571435,
      "Dewpoint": 21.400000000000002,
      "Pressure": 1010.457142857143,
      "Rain": 0.0,
      "Wind": 6.185714285714288,
      "Wind Dir.": 93.57592693811384,
      "Wind Gust": 9.8,
      "Prob Precip 0.1mm": 0.0,
      "Prob Precip 1.0mm": 0.0,
      "Prob Precip 10.0mm": 0.0,
      "Sunshine": 0.0,
      "Low Clouds": 10.285714285714286,
      "Mid Clouds": 10.000000000000002,
      "High Clouds": 0.0,
      "Condition": "Normal"
    },
    {
      "Datetime": "2026-06-30 06:00:00",
      "Temperature": 23.759999999999998,
      "Dewpoint": 21.320000000000004,
      "Pressure": 1010.96,
      "Rain": 0.0,
      "Wind": 5.82,
      "Wind Dir.": 93.0,
      "Wind Gust": 9.72,
      "Prob Precip 0.1mm": 0.5599999999999999,
      "Prob Precip 1.0mm": 0.0,
      "Prob Precip 10.0mm": 0.0,
      "Sunshine": 0.0,
      "Low Clouds": 12.8,
      "Mid Clouds": 13.600000000000003,
      "High Clouds": 0.0,
      "Condition": "Normal"
    },
    {
      "Datetime": "2026-06-30 07:00:00",
      "Temperature": 24.419999999999998,
      "Dewpoint": 21.48,
      "Pressure": 1011.5400000000001,
      "Rain": 0.0,
      "Wind": 5.380000000000001,
      "Wind Dir.": 94.20512053327312,
      "Wind Gust": 9.6,
      "Prob Precip 0.1mm": 1.2000000000000002,
      "Prob Precip 1.0mm": 0.0,
      "Prob Precip 10.0mm": 0.0,
      "Sunshine": 25.800000000000008,
      "Low Clouds": 12.4,
      "Mid Clouds": 16.0,
      "High Clouds": 0.0,
      "Condition": "Normal"
    },
    {
      "Datetime": "2026-06-30 08:00:00",
      "Temperature": 26.042857142857148,
      "Dewpoint": 21.62857142857143,
      "Pressure": 1011.9571428571429,
      "Rain": 0.0,
      "Wind": 5.928571428571429,
      "Wind Dir.": 97.13873155327585,
      "Wind Gust": 10.871428571428572,
      "Prob Precip 0.1mm": 1.8,
      "Prob Precip 1.0mm": 0.0,
      "Prob Precip 10.0mm": 0.0,
      "Sunshine": 25.285714285714292,
      "Low Clouds": 12.42857142857143,
      "Mid Clouds": 6.142857142857144,
      "High Clouds": 0.0,
      "Condition": "Normal"
    },
    {
      "Datetime": "2026-06-30 09:00:00",
      "Temperature": 27.16,
      "Dewpoint": 21.400000000000002,
      "Pressure": 1011.9600000000002,
      "Rain": 0.0,
      "Wind": 7.140000000000001,
      "Wind Dir.": 96.19889512184422,
      "Wind Gust": 13.180000000000001,
      "Prob Precip 0.1mm": 4.199999999999999,
      "Prob Precip 1.0mm": 0.0,
      "Prob Precip 10.0mm": 0.0,
      "Sunshine": 30.000000000000007,
      "Low Clouds": 16.400000000000002,
      "Mid Clouds": 4.800000000000001,
      "High Clouds": 0.0,
      "Condition": "Normal"
    },
    {
      "Datetime": "2026-06-30 10:00:00",
      "Temperature": 28.420000000000005,
      "Dewpoint": 21.14,
      "Pressure": 1011.5200000000002,
      "Rain": 0.0,
      "Wind": 6.82,
      "Wind Dir.": 95.1815967361226,
      "Wind Gust": 12.840000000000002,
      "Prob Precip 0.1mm": 6.56,
      "Prob Precip 1.0mm": 0.0,
      "Prob Precip 10.0mm": 0.0,
      "Sunshine": 30.400000000000006,
      "Low Clouds": 17.0,
      "Mid Clouds": 0.4,
      "High Clouds": 0.0,
      "Condition": "Normal"
    },
    {
      "Datetime": "2026-06-30 11:00:00",
      "Temperature": 29.51428571428572,
      "Dewpoint": 21.028571428571432,
      "Pressure": 1010.7142857142859,
      "Rain": 0.0,
      "Wind": 5.485714285714287,
      "Wind Dir.": 105.39257460265709,
      "Wind Gust": 11.500000000000002,
      "Prob Precip 0.1mm": 8.828571428571431,
      "Prob Precip 1.0mm": 0.0,
      "Prob Precip 10.0mm": 0.0,
      "Sunshine": 28.28571428571429,
      "Low Clouds": 15.714285714285717,
      "Mid Clouds": 3.000000000000001,
      "High Clouds": 0.0,
      "Condition": "Normal"
    },
    {
      "Datetime": "2026-06-30 12:00:00",
      "Temperature": 30.199999999999996,
      "Dewpoint": 20.580000000000005,
      "Pressure": 1009.9600000000002,
      "Rain": 0.0,
      "Wind": 4.5200000000000005,
      "Wind Dir.": 112.97665642296782,
      "Wind Gust": 11.440000000000001,
      "Prob Precip 0.1mm": 18.420000000000005,
      "Prob Precip 1.0mm": 2.1,
      "Prob Precip 10.0mm": 0.0,
      "Sunshine": 26.4,
      "Low Clouds": 32.00000000000001,
      "Mid Clouds": 12.600000000000001,
      "High Clouds": 0.0,
      "Condition": "Normal"
    },
    {
      "Datetime": "2026-06-30 13:00:00",
      "Temperature": 30.540000000000003,
      "Dewpoint": 20.4,
      "Pressure": 1009.1200000000001,
      "Rain": 0.02,
      "Wind": 4.640000000000001,
      "Wind Dir.": 126.74286519452444,
      "Wind Gust": 10.16,
      "Prob Precip 0.1mm": 27.759999999999998,
      "Prob Precip 1.0mm": 4.1000000000000005,
      "Prob Precip 10.0mm": 0.0,
      "Sunshine": 21.000000000000004,
      "Low Clouds": 49.00000000000001,
      "Mid Clouds": 22.200000000000003,
      "High Clouds": 0.0,
      "Condition": "Normal"
    },
    {
      "Datetime": "2026-06-30 14:00:00",
      "Temperature": 30.55714285714286,
      "Dewpoint": 20.71428571428572,
      "Pressure": 1008.3857142857145,
      "Rain": 0.018571428571428576,
      "Wind": 4.242857142857144,
      "Wind Dir.": 150.11550757100153,
      "Wind Gust": 9.02857142857143,
      "Prob Precip 0.1mm": 36.21428571428572,
      "Prob Precip 1.0mm": 5.942857142857144,
      "Prob Precip 10.0mm": 0.0,
      "Sunshine": 17.571428571428573,
      "Low Clouds": 38.42857142857143,
      "Mid Clouds": 17.000000000000004,
      "High Clouds": 0.0,
      "Condition": "Normal"
    },
    {
      "Datetime": "2026-06-30 15:00:00",
      "Temperature": 30.340000000000003,
      "Dewpoint": 20.66,
      "Pressure": 1007.96,
      "Rain": 0.04,
      "Wind": 3.6799999999999997,
      "Wind Dir.": 151.67120488448433,
      "Wind Gust": 8.0,
      "Prob Precip 0.1mm": 39.6,
      "Prob Precip 1.0mm": 8.24,
      "Prob Precip 10.0mm": 0.0,
      "Sunshine": 16.4,
      "Low Clouds": 40.800000000000004,
      "Mid Clouds": 20.0,
      "High Clouds": 0.0,
      "Condition": "Normal"
    },
    {
      "Datetime": "2026-06-30 16:00:00",
      "Temperature": 30.100000000000005,
      "Dewpoint": 20.96,
      "Pressure": 1008.0600000000001,
      "Rain": 0.0,
      "Wind": 2.8200000000000003,
      "Wind Dir.": 141.26985000508643,
      "Wind Gust": 7.44,
      "Prob Precip 0.1mm": 42.1,
      "Prob Precip 1.0mm": 10.379999999999999,
      "Prob Precip 10.0mm": 0.0,
      "Sunshine": 14.799999999999999,
      "Low Clouds": 32.8,
      "Mid Clouds": 14.600000000000001,
      "High Clouds": 0.0,
      "Condition": "Normal"
    },
    {
      "Datetime": "2026-06-30 17:00:00",
      "Temperature": 29.142857142857146,
      "Dewpoint": 21.58571428571429,
      "Pressure": 1008.5285714285715,
      "Rain": 0.024285714285714292,
      "Wind": 3.4857142857142867,
      "Wind Dir.": 175.7754762457993,
      "Wind Gust": 7.485714285714287,
      "Prob Precip 0.1mm": 44.157142857142865,
      "Prob Precip 1.0mm": 11.542857142857144,
      "Prob Precip 10.0mm": 0.0,
      "Sunshine": 14.571428571428573,
      "Low Clouds": 17.28571428571429,
      "Mid Clouds": 9.571428571428573,
      "High Clouds": 0.0,
      "Condition": "Normal"
    },
    {
      "Datetime": "2026-06-30 18:00:00",
      "Temperature": 28.020000000000007,
      "Dewpoint": 21.400000000000006,
      "Pressure": 1009.18,
      "Rain": 0.0,
      "Wind": 3.560000000000001,
      "Wind Dir.": 92.3369671220511,
      "Wind Gust": 7.5600000000000005,
      "Prob Precip 0.1mm": 37.32,
      "Prob Precip 1.0mm": 8.280000000000001,
      "Prob Precip 10.0mm": 0.0,
      "Sunshine": 13.0,
      "Low Clouds": 22.6,
      "Mid Clouds": 11.200000000000001,
      "High Clouds": 0.0,
      "Condition": "Normal"
    },
    {
      "Datetime": "2026-06-30 19:00:00",
      "Temperature": 27.000000000000004,
      "Dewpoint": 21.860000000000003,
      "Pressure": 1009.9800000000001,
      "Rain": 0.02,
      "Wind": 4.760000000000001,
      "Wind Dir.": 76.66618757935895,
      "Wind Gust": 8.42,
      "Prob Precip 0.1mm": 30.020000000000003,
      "Prob Precip 1.0mm": 4.140000000000001,
      "Prob Precip 10.0mm": 0.0,
      "Sunshine": 0.0,
      "Low Clouds": 28.6,
      "Mid Clouds": 13.399999999999999,
      "High Clouds": 0.0,
      "Condition": "Normal"
    },
    {
      "Datetime": "2026-06-30 20:00:00",
      "Temperature": 26.585714285714293,
      "Dewpoint": 22.185714285714287,
      "Pressure": 1010.6428571428573,
      "Rain": 0.004285714285714286,
      "Wind": 4.7,
      "Wind Dir.": 76.6405980331078,
      "Wind Gust": 8.242857142857144,
      "Prob Precip 0.1mm": 21.914285714285715,
      "Prob Precip 1.0mm": 0.0,
      "Prob Precip 10.0mm": 0.0,
      "Sunshine": 1.7142857142857146,
      "Low Clouds": 10.000000000000002,
      "Mid Clouds": 6.000000000000002,
      "High Clouds": 0.0,
      "Condition": "Normal"
    },
    {
      "Datetime": "2026-06-30 21:00:00",
      "Temperature": 25.620000000000005,
      "Dewpoint": 21.540000000000003,
      "Pressure": 1011.3800000000001,
      "Rain": 0.0,
      "Wind": 5.74,
      "Wind Dir.": 89.0064094825228,
      "Wind Gust": 9.280000000000001,
      "Prob Precip 0.1mm": 15.18,
      "Prob Precip 1.0mm": 0.0,
      "Prob Precip 10.0mm": 0.0,
      "Sunshine": 0.0,
      "Low Clouds": 8.6,
      "Mid Clouds": 3.0000000000000004,
      "High Clouds": 0.0,
      "Condition": "Normal"
    },
    {
      "Datetime": "2026-06-30 22:00:00",
      "Temperature": 25.120000000000005,
      "Dewpoint": 21.62,
      "Pressure": 1011.64,
      "Rain": 0.0,
      "Wind": 5.400000000000001,
      "Wind Dir.": 88.40447752571562,
      "Wind Gust": 8.979999999999999,
      "Prob Precip 0.1mm": 7.62,
      "Prob Precip 1.0mm": 0.0,
      "Prob Precip 10.0mm": 0.0,
      "Sunshine": 0.0,
      "Low Clouds": 3.4000000000000004,
      "Mid Clouds": 6.6,
      "High Clouds": 0.0,
      "Condition": "Normal"
    },
    {
      "Datetime": "2026-06-30 23:00:00",
      "Temperature": 25.228571428571435,
      "Dewpoint": 21.742857142857144,
      "Pressure": 1011.6000000000001,
      "Rain": 0.0,
      "Wind": 5.385714285714286,
      "Wind Dir.": 88.59246083853333,
      "Wind Gust": 8.571428571428573,
      "Prob Precip 0.1mm": 0.0,
      "Prob Precip 1.0mm": 0.0,
      "Prob Precip 10.0mm": 0.0,
      "Sunshine": 0.0,
      "Low Clouds": 0.14285714285714288,
      "Mid Clouds": 7.714285714285715,
      "High Clouds": 0.0,
      "Condition": "Normal"
    },
    {
      "Datetime": "2026-07-01 00:00:00",
      "Temperature": 24.500000000000004,
      "Dewpoint": 21.200000000000003,
      "Pressure": 1011.5400000000001,
      "Rain": 0.0,
      "Wind": 5.2,
      "Wind Dir.": 94.57245752749805,
      "Wind Gust": 8.860000000000001,
      "Prob Precip 0.1mm": 0.0,
      "Prob Precip 1.0mm": 0.0,
      "Prob Precip 10.0mm": 0.0,
      "Sunshine": 0.0,
      "Low Clouds": 0.2,
      "Mid Clouds": 13.8,
      "High Clouds": 0.0,
      "Condition": "Normal"
    },
    {
      "Datetime": "2026-07-01 01:00:00",
      "Temperature": 24.200000000000003,
      "Dewpoint": 21.0,
      "Pressure": 1011.1400000000001,
      "Rain": 0.0,
      "Wind": 5.4,
      "Wind Dir.": 99.48296933309875,
      "Wind Gust": 8.72,
      "Prob Precip 0.1mm": 0.0,
      "Prob Precip 1.0mm": 0.0,
      "Prob Precip 10.0mm": 0.0,
      "Sunshine": 0.0,
      "Low Clouds": 0.0,
      "Mid Clouds": 14.400000000000002,
      "High Clouds": 0.0,
      "Condition": "Normal"
    },
    {
      "Datetime": "2026-07-01 02:00:00",
      "Temperature": 24.41428571428572,
      "Dewpoint": 21.142857142857146,
      "Pressure": 1010.6714285714288,
      "Rain": 0.0,
      "Wind": 5.942857142857143,
      "Wind Dir.": 101.42565519470784,
      "Wind Gust": 8.62857142857143,
      "Prob Precip 0.1mm": 0.0,
      "Prob Precip 1.0mm": 0.0,
      "Prob Precip 10.0mm": 0.0,
      "Sunshine": 0.0,
      "Low Clouds": 0.0,
      "Mid Clouds": 8.571428571428573,
      "High Clouds": 0.0,
      "Condition": "Normal"
    },
    {
      "Datetime": "2026-07-01 03:00:00",
      "Temperature": 24.5,
      "Dewpoint": 20.925,
      "Pressure": 1010.4000000000001,
      "Rain": 0.0,
      "Wind": 5.925000000000001,
      "Wind Dir.": 107.76029326408576,
      "Wind Gust": 9.325,
      "Prob Precip 0.1mm": 0.0,
      "Prob Precip 1.0mm": 0.0,
      "Prob Precip 10.0mm": 0.0,
      "Sunshine": 0.0,
      "Low Clouds": 0.0,
      "Mid Clouds": 13.25,
      "High Clouds": 0.0,
      "Condition": "Normal"
    },
    {
      "Datetime": "2026-07-01 04:00:00",
      "Temperature": 24.25,
      "Dewpoint": 20.875,
      "Pressure": 1010.45,
      "Rain": 0.0,
      "Wind": 5.65,
      "Wind Dir.": 107.49478052605436,
      "Wind Gust": 8.625000000000002,
      "Prob Precip 0.1mm": 0.0,
      "Prob Precip 1.0mm": 0.0,
      "Prob Precip 10.0mm": 0.0,
      "Sunshine": 0.0,
      "Low Clouds": 0.0,
      "Mid Clouds": 12.75,
      "High Clouds": 0.0,
      "Condition": "Normal"
    },
    {
      "Datetime": "2026-07-01 05:00:00",
      "Temperature": 23.842857142857145,
      "Dewpoint": 20.742857142857144,
      "Pressure": 1010.7142857142859,
      "Rain": 0.0,
      "Wind": 5.614285714285715,
      "Wind Dir.": 100.13647621373713,
      "Wind Gust": 8.257142857142858,
      "Prob Precip 0.1mm": 0.0,
      "Prob Precip 1.0mm": 0.0,
      "Prob Precip 10.0mm": 0.0,
      "Sunshine": 0.0,
      "Low Clouds": 2.0000000000000004,
      "Mid Clouds": 6.571428571428573,
      "High Clouds": 0.0,
      "Condition": "Normal"
    },
    {
      "Datetime": "2026-07-01 06:00:00",
      "Temperature": 23.825,
      "Dewpoint": 20.825,
      "Pressure": 1011.1250000000001,
      "Rain": 0.0,
      "Wind": 5.375000000000001,
      "Wind Dir.": 100.23229581173445,
      "Wind Gust": 7.8500000000000005,
      "Prob Precip 0.1mm": 0.0,
      "Prob Precip 1.0mm": 0.0,
      "Prob Precip 10.0mm": 0.0,
      "Sunshine": 0.0,
      "Low Clouds": 0.0,
      "Mid Clouds": 9.75,
      "High Clouds": 0.0,
      "Condition": "Normal"
    },
    {
      "Datetime": "2026-07-01 07:00:00",
      "Temperature": 24.55,
      "Dewpoint": 20.975,
      "Pressure": 1011.8249999999999,
      "Rain": 0.0,
      "Wind": 4.9750000000000005,
      "Wind Dir.": 97.48061771313391,
      "Wind Gust": 7.825,
      "Prob Precip 0.1mm": 0.0,
      "Prob Precip 1.0mm": 0.0,
      "Prob Precip 10.0mm": 0.0,
      "Sunshine": 39.0,
      "Low Clouds": 0.0,
      "Mid Clouds": 8.25,
      "High Clouds": 0.0,
      "Condition": "Normal"
    },
    {
      "Datetime": "2026-07-01 08:00:00",
      "Temperature": 26.000000000000004,
      "Dewpoint": 20.885714285714286,
      "Pressure": 1012.4000000000001,
      "Rain": 0.0,
      "Wind": 5.328571428571429,
      "Wind Dir.": 94.12370344434935,
      "Wind Gust": 9.12857142857143,
      "Prob Precip 0.1mm": 0.0,
      "Prob Precip 1.0mm": 0.0,
      "Prob Precip 10.0mm": 0.0,
      "Sunshine": 30.000000000000007,
      "Low Clouds": 1.8571428571428574,
      "Mid Clouds": 0.8571428571428573,
      "High Clouds": 0.0,
      "Condition": "Normal"
    },
    {
      "Datetime": "2026-07-01 09:00:00",
      "Temperature": 27.8,
      "Dewpoint": 20.799999999999997,
      "Pressure": 1012.5,
      "Rain": 0.0,
      "Wind": 4.8500000000000005,
      "Wind Dir.": 91.47229411979737,
      "Wind Gust": 9.475,
      "Prob Precip 0.1mm": 0.1,
      "Prob Precip 1.0mm": 0.0,
      "Prob Precip 10.0mm": 0.0,
      "Sunshine": 44.50000000000001,
      "Low Clouds": 7.5,
      "Mid Clouds": 0.0,
      "High Clouds": 0.0,
      "Condition": "Normal"
    },
    {
      "Datetime": "2026-07-01 10:00:00",
      "Temperature": 29.024999999999995,
      "Dewpoint": 20.25,
      "Pressure": 1012.2249999999998,
      "Rain": 0.0,
      "Wind": 3.9250000000000003,
      "Wind Dir.": 78.52535027129196,
      "Wind Gust": 9.049999999999999,
      "Prob Precip 0.1mm": 0.2,
      "Prob Precip 1.0mm": 0.0,
      "Prob Precip 10.0mm": 0.0,
      "Sunshine": 44.25,
      "Low Clouds": 4.75,
      "Mid Clouds": 0.0,
      "High Clouds": 0.0,
      "Condition": "Normal"
    },
    {
      "Datetime": "2026-07-01 11:00:00",
      "Temperature": 29.48571428571429,
      "Dewpoint": 20.242857142857147,
      "Pressure": 1011.3571428571431,
      "Rain": 0.0,
      "Wind": 3.6142857142857157,
      "Wind Dir.": 96.7661256407969,
      "Wind Gust": 9.100000000000001,
      "Prob Precip 0.1mm": 0.17142857142857143,
      "Prob Precip 1.0mm": 0.0,
      "Prob Precip 10.0mm": 0.0,
      "Sunshine": 32.57142857142858,
      "Low Clouds": 7.571428571428573,
      "Mid Clouds": 0.0,
      "High Clouds": 0.0,
      "Condition": "Normal"
    },
    {
      "Datetime": "2026-07-01 12:00:00",
      "Temperature": 30.2,
      "Dewpoint": 20.4,
      "Pressure": 1010.5749999999999,
      "Rain": 0.0,
      "Wind": 4.6000000000000005,
      "Wind Dir.": 183.52006897581543,
      "Wind Gust": 9.2,
      "Prob Precip 0.1mm": 9.85,
      "Prob Precip 1.0mm": 0.75,
      "Prob Precip 10.0mm": 0.0,
      "Sunshine": 41.00000000000001,
      "Low Clouds": 13.25,
      "Mid Clouds": 0.0,
      "High Clouds": 0.0,
      "Condition": "Normal"
    },
    {
      "Datetime": "2026-07-01 13:00:00",
      "Temperature": 30.600000000000005,
      "Dewpoint": 20.1,
      "Pressure": 1009.6249999999999,
      "Rain": 0.0,
      "Wind": 4.749999999999999,
      "Wind Dir.": 196.6530860625843,
      "Wind Gust": 8.65,
      "Prob Precip 0.1mm": 19.475000000000005,
      "Prob Precip 1.0mm": 1.5,
      "Prob Precip 10.0mm": 0.0,
      "Sunshine": 36.00000000000001,
      "Low Clouds": 19.0,
      "Mid Clouds": 19.75,
      "High Clouds": 0.0,
      "Condition": "Normal"
    },
    {
      "Datetime": "2026-07-01 14:00:00",
      "Temperature": 30.014285714285716,
      "Dewpoint": 20.7,
      "Pressure": 1008.8000000000002,
      "Rain": 0.0,
      "Wind": 5.871428571428572,
      "Wind Dir.": 237.222248717249,
      "Wind Gust": 10.042857142857143,
      "Prob Precip 0.1mm": 27.042857142857144,
      "Prob Precip 1.0mm": 1.2714285714285716,
      "Prob Precip 10.0mm": 0.0,
      "Sunshine": 26.428571428571434,
      "Low Clouds": 27.571428571428577,
      "Mid Clouds": 13.142857142857146,
      "High Clouds": 0.0,
      "Condition": "Normal"
    },
    {
      "Datetime": "2026-07-01 15:00:00",
      "Temperature": 29.400000000000002,
      "Dewpoint": 21.975,
      "Pressure": 1008.4749999999999,
      "Rain": 0.0,
      "Wind": 7.175,
      "Wind Dir.": 264.13563391962316,
      "Wind Gust": 10.675,
      "Prob Precip 0.1mm": 32.0,
      "Prob Precip 1.0mm": 7.025,
      "Prob Precip 10.0mm": 0.0,
      "Sunshine": 36.00000000000001,
      "Low Clouds": 22.25,
      "Mid Clouds": 25.250000000000004,
      "High Clouds": 0.0,
      "Condition": "Normal"
    },
    {
      "Datetime": "2026-07-01 16:00:00",
      "Temperature": 28.775000000000002,
      "Dewpoint": 22.875,
      "Pressure": 1008.4249999999998,
      "Rain": 0.0,
      "Wind": 7.125,
      "Wind Dir.": 261.4966378659755,
      "Wind Gust": 10.525,
      "Prob Precip 0.1mm": 35.0,
      "Prob Precip 1.0mm": 11.825,
      "Prob Precip 10.0mm": 0.0,
      "Sunshine": 36.75,
      "Low Clouds": 12.25,
      "Mid Clouds": 1.75,
      "High Clouds": 0.0,
      "Condition": "Normal"
    },
    {
      "Datetime": "2026-07-01 17:00:00",
      "Temperature": 28.300000000000004,
      "Dewpoint": 22.642857142857142,
      "Pressure": 1008.7857142857144,
      "Rain": 0.014285714285714289,
      "Wind": 5.785714285714286,
      "Wind Dir.": 229.84588464151864,
      "Wind Gust": 10.25714285714286,
      "Prob Precip 0.1mm": 34.35714285714287,
      "Prob Precip 1.0mm": 14.642857142857144,
      "Prob Precip 10.0mm": 0.0,
      "Sunshine": 27.14285714285715,
      "Low Clouds": 14.000000000000004,
      "Mid Clouds": 4.857142857142858,
      "High Clouds": 0.0,
      "Condition": "Normal"
    },
    {
      "Datetime": "2026-07-01 18:00:00",
      "Temperature": 27.575,
      "Dewpoint": 22.949999999999996,
      "Pressure": 1009.3499999999999,
      "Rain": 0.0,
      "Wind": 5.65,
      "Wind Dir.": 250.4082397957651,
      "Wind Gust": 8.675,
      "Prob Precip 0.1mm": 34.800000000000004,
      "Prob Precip 1.0mm": 11.075,
      "Prob Precip 10.0mm": 0.0,
      "Sunshine": 29.75,
      "Low Clouds": 13.0,
      "Mid Clouds": 8.75,
      "High Clouds": 0.0,
      "Condition": "Normal"
    },
    {
      "Datetime": "2026-07-01 19:00:00",
      "Temperature": 27.175,
      "Dewpoint": 22.85,
      "Pressure": 1010.0500000000001,
      "Rain": 0.0,
      "Wind": 3.2250000000000005,
      "Wind Dir.": 176.18013653395877,
      "Wind Gust": 6.6000000000000005,
      "Prob Precip 0.1mm": 31.575,
      "Prob Precip 1.0mm": 5.549999999999999,
      "Prob Precip 10.0mm": 0.0,
      "Sunshine": 0.0,
      "Low Clouds": 19.0,
      "Mid Clouds": 2.0,
      "High Clouds": 0.0,
      "Condition": "Normal"
    },
    {
      "Datetime": "2026-07-01 20:00:00",
      "Temperature": 26.428571428571434,
      "Dewpoint": 22.6,
      "Pressure": 1010.8000000000002,
      "Rain": 0.0,
      "Wind": 3.3142857142857154,
      "Wind Dir.": 80.19990616218202,
      "Wind Gust": 6.242857142857145,
      "Prob Precip 0.1mm": 25.900000000000002,
      "Prob Precip 1.0mm": 0.0,
      "Prob Precip 10.0mm": 0.0,
      "Sunshine": 2.0000000000000004,
      "Low Clouds": 6.285714285714287,
      "Mid Clouds": 0.42857142857142866,
      "High Clouds": 0.0,
      "Condition": "Normal"
    },
    {
      "Datetime": "2026-07-01 21:00:00",
      "Temperature": 25.875,
      "Dewpoint": 23.175,
      "Pressure": 1011.6500000000001,
      "Rain": 0.0,
      "Wind": 4.7250000000000005,
      "Wind Dir.": 70.0,
      "Wind Gust": 7.299999999999999,
      "Prob Precip 0.1mm": 22.274999999999995,
      "Prob Precip 1.0mm": 0.0,
      "Prob Precip 10.0mm": 0.0,
      "Sunshine": 0.0,
      "Low Clouds": 2.9999999999999996,
      "Mid Clouds": 0.0,
      "High Clouds": 0.0,
      "Condition": "Normal"
    },
    {
      "Datetime": "2026-07-01 22:00:00",
      "Temperature": 25.3,
      "Dewpoint": 23.124999999999996,
      "Pressure": 1011.9499999999998,
      "Rain": 0.0,
      "Wind": 4.8500000000000005,
      "Wind Dir.": 89.24317443888982,
      "Wind Gust": 7.699999999999999,
      "Prob Precip 0.1mm": 16.149999999999995,
      "Prob Precip 1.0mm": 0.0,
      "Prob Precip 10.0mm": 0.0,
      "Sunshine": 0.0,
      "Low Clouds": 2.25,
      "Mid Clouds": 0.0,
      "High Clouds": 0.0,
      "Condition": "Normal"
    },
    {
      "Datetime": "2026-07-01 23:00:00",
      "Temperature": 25.028571428571436,
      "Dewpoint": 22.500000000000004,
      "Pressure": 1012.1142857142859,
      "Rain": 0.0,
      "Wind": 5.000000000000001,
      "Wind Dir.": 94.52648709104307,
      "Wind Gust": 7.942857142857144,
      "Prob Precip 0.1mm": 10.885714285714286,
      "Prob Precip 1.0mm": 0.0,
      "Prob Precip 10.0mm": 0.0,
      "Sunshine": 0.0,
      "Low Clouds": 6.000000000000001,
      "Mid Clouds": 0.0,
      "High Clouds": 0.0,
      "Condition": "Normal"
    },
    {
      "Datetime": "2026-07-02 00:00:00",
      "Temperature": 24.975,
      "Dewpoint": 22.525,
      "Pressure": 1011.9499999999998,
      "Rain": 0.0,
      "Wind": 5.4,
      "Wind Dir.": 103.98930787953357,
      "Wind Gust": 8.374999999999998,
      "Prob Precip 0.1mm": 7.800000000000001,
      "Prob Precip 1.0mm": 0.0,
      "Prob Precip 10.0mm": 0.0,
      "Sunshine": 0.0,
      "Low Clouds": 7.5,
      "Mid Clouds": 0.0,
      "High Clouds": 0.0,
      "Condition": "Normal"
    },
    {
      "Datetime": "2026-07-02 01:00:00",
      "Temperature": 24.75,
      "Dewpoint": 22.65,
      "Pressure": 1011.5249999999999,
      "Rain": 0.0,
      "Wind": 5.375000000000001,
      "Wind Dir.": 104.24664049119616,
      "Wind Gust": 8.125,
      "Prob Precip 0.1mm": 5.475,
      "Prob Precip 1.0mm": 0.0,
      "Prob Precip 10.0mm": 0.0,
      "Sunshine": 0.0,
      "Low Clouds": 9.5,
      "Mid Clouds": 0.0,
      "High Clouds": 0.0,
      "Condition": "Normal"
    },
    {
      "Datetime": "2026-07-02 02:00:00",
      "Temperature": 24.442857142857147,
      "Dewpoint": 22.5,
      "Pressure": 1011.1714285714287,
      "Rain": 0.024285714285714292,
      "Wind": 5.071428571428572,
      "Wind Dir.": 99.02277091188125,
      "Wind Gust": 7.714285714285714,
      "Prob Precip 0.1mm": 2.9142857142857146,
      "Prob Precip 1.0mm": 0.0,
      "Prob Precip 10.0mm": 0.0,
      "Sunshine": 0.0,
      "Low Clouds": 5.000000000000001,
      "Mid Clouds": 0.14285714285714288,
      "High Clouds": 0.0,
      "Condition": "Normal"
    },
    {
      "Datetime": "2026-07-02 03:00:00",
      "Temperature": 25.2,
      "Dewpoint": 22.4,
      "Pressure": 1010.6,
      "Rain": 0.0,
      "Wind": 6.5,
      "Wind Dir.": 96.00000000000001,
      "Wind Gust": 8.1,
      "Prob Precip 0.1mm": 1.7,
      "Prob Precip 1.0mm": 0.0,
      "Prob Precip 10.0mm": 0.0,
      "Sunshine": 0.0,
      "Low Clouds": 1.0,
      "Mid Clouds": 0.0,
      "High Clouds": 0.0,
      "Condition": "Normal"
    },
    {
      "Datetime": "2026-07-02 04:00:00",
      "Temperature": 25.0,
      "Dewpoint": 22.4,
      "Pressure": 1010.5000000000001,
      "Rain": 0.0,
      "Wind": 6.5,
      "Wind Dir.": 94.0,
      "Wind Gust": 7.6,
      "Prob Precip 0.1mm": 0.8999999999999999,
      "Prob Precip 1.0mm": 0.0,
      "Prob Precip 10.0mm": 0.0,
      "Sunshine": 0.0,
      "Low Clouds": 2.0,
      "Mid Clouds": 0.0,
      "High Clouds": 0.0,
      "Condition": "Normal"
    },
    {
      "Datetime": "2026-07-02 05:00:00",
      "Temperature": 23.928571428571427,
      "Dewpoint": 22.042857142857144,
      "Pressure": 1011.1142857142859,
      "Rain": 0.0,
      "Wind": 4.92857142857143,
      "Wind Dir.": 97.01239574707176,
      "Wind Gust": 7.714285714285715,
      "Prob Precip 0.1mm": 0.0,
      "Prob Precip 1.0mm": 0.0,
      "Prob Precip 10.0mm": 0.0,
      "Sunshine": 0.0,
      "Low Clouds": 0.5714285714285715,
      "Mid Clouds": 0.0,
      "High Clouds": 0.0,
      "Condition": "Normal"
    },
    {
      "Datetime": "2026-07-02 06:00:00",
      "Temperature": 24.9,
      "Dewpoint": 22.2,
      "Pressure": 1011.0,
      "Rain": 0.0,
      "Wind": 6.5,
      "Wind Dir.": 87.0,
      "Wind Gust": 7.6,
      "Prob Precip 0.1mm": 0.0,
      "Prob Precip 1.0mm": 0.0,
      "Prob Precip 10.0mm": 0.0,
      "Sunshine": 0.0,
      "Low Clouds": 4.0,
      "Mid Clouds": 0.0,
      "High Clouds": 0.0,
      "Condition": "Normal"
    },
    {
      "Datetime": "2026-07-02 07:00:00",
      "Temperature": 25.2,
      "Dewpoint": 22.1,
      "Pressure": 1011.3999999999999,
      "Rain": 0.0,
      "Wind": 5.9,
      "Wind Dir.": 89.0,
      "Wind Gust": 7.0,
      "Prob Precip 0.1mm": 0.0,
      "Prob Precip 1.0mm": 0.0,
      "Prob Precip 10.0mm": 0.0,
      "Sunshine": 50.0,
      "Low Clouds": 0.0,
      "Mid Clouds": 0.0,
      "High Clouds": 0.0,
      "Condition": "Normal"
    },
    {
      "Datetime": "2026-07-02 08:00:00",
      "Temperature": 26.000000000000007,
      "Dewpoint": 21.985714285714288,
      "Pressure": 1012.5000000000002,
      "Rain": 0.0,
      "Wind": 4.942857142857144,
      "Wind Dir.": 90.60355409775099,
      "Wind Gust": 9.32857142857143,
      "Prob Precip 0.1mm": 0.0,
      "Prob Precip 1.0mm": 0.0,
      "Prob Precip 10.0mm": 0.0,
      "Sunshine": 22.85714285714286,
      "Low Clouds": 0.8571428571428572,
      "Mid Clouds": 0.0,
      "High Clouds": 0.0,
      "Condition": "Normal"
    },
    {
      "Datetime": "2026-07-02 09:00:00",
      "Temperature": 27.2,
      "Dewpoint": 21.5,
      "Pressure": 1012.3999999999999,
      "Rain": 0.0,
      "Wind": 3.8,
      "Wind Dir.": 80.0,
      "Wind Gust": 6.5,
      "Prob Precip 0.1mm": 2.3,
      "Prob Precip 1.0mm": 0.0,
      "Prob Precip 10.0mm": 0.0,
      "Sunshine": 59.00000000000001,
      "Low Clouds": 0.0,
      "Mid Clouds": 0.0,
      "High Clouds": 0.0,
      "Condition": "Normal"
    },
    {
      "Datetime": "2026-07-02 10:00:00",
      "Temperature": 28.4,
      "Dewpoint": 20.9,
      "Pressure": 1012.2,
      "Rain": 0.0,
      "Wind": 1.6,
      "Wind Dir.": 59.99999999999999,
      "Wind Gust": 5.4,
      "Prob Precip 0.1mm": 4.6,
      "Prob Precip 1.0mm": 0.0,
      "Prob Precip 10.0mm": 0.0,
      "Sunshine": 59.00000000000001,
      "Low Clouds": 0.0,
      "Mid Clouds": 0.0,
      "High Clouds": 0.0,
      "Condition": "Normal"
    },
    {
      "Datetime": "2026-07-02 11:00:00",
      "Temperature": 29.185714285714287,
      "Dewpoint": 21.271428571428576,
      "Pressure": 1011.7000000000002,
      "Rain": 0.0,
      "Wind": 4.542857142857144,
      "Wind Dir.": 77.96851462117887,
      "Wind Gust": 10.342857142857145,
      "Prob Precip 0.1mm": 9.85714285714286,
      "Prob Precip 1.0mm": 0.0,
      "Prob Precip 10.0mm": 0.0,
      "Sunshine": 26.14285714285715,
      "Low Clouds": 21.28571428571429,
      "Mid Clouds": 5.000000000000001,
      "High Clouds": 0.0,
      "Condition": "Normal"
    },
    {
      "Datetime": "2026-07-02 12:00:00",
      "Temperature": 29.100000000000005,
      "Dewpoint": 21.5,
      "Pressure": 1010.3,
      "Rain": 0.0,
      "Wind": 6.5,
      "Wind Dir.": 273.0,
      "Wind Gust": 4.9,
      "Prob Precip 0.1mm": 14.0,
      "Prob Precip 1.0mm": 5.1,
      "Prob Precip 10.0mm": 0.0,
      "Sunshine": 57.0,
      "Low Clouds": 12.0,
      "Mid Clouds": 0.0,
      "High Clouds": 0.0,
      "Condition": "Normal"
    },
    {
      "Datetime": "2026-07-02 13:00:00",
      "Temperature": 28.5,
      "Dewpoint": 22.2,
      "Pressure": 1009.6,
      "Rain": 0.0,
      "Wind": 10.3,
      "Wind Dir.": 252.0,
      "Wind Gust": 6.5,
      "Prob Precip 0.1mm": 21.1,
      "Prob Precip 1.0mm": 10.3,
      "Prob Precip 10.0mm": 0.0,
      "Sunshine": 53.0,
      "Low Clouds": 19.0,
      "Mid Clouds": 0.0,
      "High Clouds": 0.0,
      "Condition": "Normal"
    },
    {
      "Datetime": "2026-07-02 14:00:00",
      "Temperature": 29.92857142857143,
      "Dewpoint": 21.3,
      "Pressure": 1009.3428571428574,
      "Rain": 0.024285714285714292,
      "Wind": 6.014285714285716,
      "Wind Dir.": 162.48083644338035,
      "Wind Gust": 10.657142857142858,
      "Prob Precip 0.1mm": 31.98571428571429,
      "Prob Precip 1.0mm": 18.32857142857143,
      "Prob Precip 10.0mm": 0.0,
      "Sunshine": 20.857142857142858,
      "Low Clouds": 15.142857142857146,
      "Mid Clouds": 10.714285714285715,
      "High Clouds": 0.0,
      "Condition": "Normal"
    },
    {
      "Datetime": "2026-07-02 15:00:00",
      "Temperature": 27.8,
      "Dewpoint": 22.6,
      "Pressure": 1009.0,
      "Rain": 0.0,
      "Wind": 9.2,
      "Wind Dir.": 229.0,
      "Wind Gust": 8.1,
      "Prob Precip 0.1mm": 32.3,
      "Prob Precip 1.0mm": 17.7,
      "Prob Precip 10.0mm": 0.0,
      "Sunshine": 43.0,
      "Low Clouds": 52.0,
      "Mid Clouds": 0.0,
      "High Clouds": 0.0,
      "Condition": "Normal"
    },
    {
      "Datetime": "2026-07-02 16:00:00",
      "Temperature": 28.0,
      "Dewpoint": 22.6,
      "Pressure": 1009.0,
      "Rain": 0.0,
      "Wind": 8.6,
      "Wind Dir.": 227.0,
      "Wind Gust": 7.0,
      "Prob Precip 0.1mm": 36.5,
      "Prob Precip 1.0mm": 20.0,
      "Prob Precip 10.0mm": 0.0,
      "Sunshine": 38.0,
      "Low Clouds": 33.0,
      "Mid Clouds": 0.0,
      "High Clouds": 0.0,
      "Condition": "Normal"
    },
    {
      "Datetime": "2026-07-02 17:00:00",
      "Temperature": 28.985714285714288,
      "Dewpoint": 22.628571428571433,
      "Pressure": 1009.4285714285714,
      "Rain": 0.02285714285714286,
      "Wind": 3.957142857142858,
      "Wind Dir.": 214.57475450831274,
      "Wind Gust": 8.700000000000001,
      "Prob Precip 0.1mm": 45.17142857142858,
      "Prob Precip 1.0mm": 24.500000000000004,
      "Prob Precip 10.0mm": 0.0,
      "Sunshine": 22.714285714285715,
      "Low Clouds": 12.571428571428575,
      "Mid Clouds": 7.42857142857143,
      "High Clouds": 0.0,
      "Condition": "Normal"
    },
    {
      "Datetime": "2026-07-02 18:00:00",
      "Temperature": 27.9,
      "Dewpoint": 22.6,
      "Pressure": 1009.8,
      "Rain": 0.1,
      "Wind": 4.3,
      "Wind Dir.": 228.0,
      "Wind Gust": 3.8,
      "Prob Precip 0.1mm": 35.5,
      "Prob Precip 1.0mm": 14.8,
      "Prob Precip 10.0mm": 0.0,
      "Sunshine": 49.0,
      "Low Clouds": 0.0,
      "Mid Clouds": 0.0,
      "High Clouds": 0.0,
      "Condition": "Light Rain"
    },
    {
      "Datetime": "2026-07-02 19:00:00",
      "Temperature": 27.8,
      "Dewpoint": 22.3,
      "Pressure": 1010.3,
      "Rain": 0.0,
      "Wind": 1.1,
      "Wind Dir.": 36.0,
      "Wind Gust": 4.3,
      "Prob Precip 0.1mm": 30.4,
      "Prob Precip 1.0mm": 7.4,
      "Prob Precip 10.0mm": 0.0,
      "Sunshine": 0.0,
      "Low Clouds": 1.0,
      "Mid Clouds": 0.0,
      "High Clouds": 0.0,
      "Condition": "Normal"
    },
    {
      "Datetime": "2026-07-02 20:00:00",
      "Temperature": 26.700000000000003,
      "Dewpoint": 22.814285714285717,
      "Pressure": 1011.4000000000001,
      "Rain": 0.004285714285714286,
      "Wind": 4.028571428571429,
      "Wind Dir.": 75.00820381917642,
      "Wind Gust": 7.000000000000001,
      "Prob Precip 0.1mm": 27.85714285714287,
      "Prob Precip 1.0mm": 0.0,
      "Prob Precip 10.0mm": 0.0,
      "Sunshine": 5.000000000000001,
      "Low Clouds": 8.714285714285715,
      "Mid Clouds": 1.142857142857143,
      "High Clouds": 0.0,
      "Condition": "Normal"
    },
    {
      "Datetime": "2026-07-02 21:00:00",
      "Temperature": 26.6,
      "Dewpoint": 22.5,
      "Pressure": 1012.1,
      "Rain": 0.0,
      "Wind": 7.0,
      "Wind Dir.": 66.0,
      "Wind Gust": 8.6,
      "Prob Precip 0.1mm": 20.1,
      "Prob Precip 1.0mm": 0.0,
      "Prob Precip 10.0mm": 0.0,
      "Sunshine": 0.0,
      "Low Clouds": 0.0,
      "Mid Clouds": 0.0,
      "High Clouds": 0.0,
      "Condition": "Normal"
    },
    {
      "Datetime": "2026-07-02 22:00:00",
      "Temperature": 25.9,
      "Dewpoint": 22.6,
      "Pressure": 1012.3999999999999,
      "Rain": 0.0,
      "Wind": 7.6,
      "Wind Dir.": 86.0,
      "Wind Gust": 9.2,
      "Prob Precip 0.1mm": 14.9,
      "Prob Precip 1.0mm": 0.0,
      "Prob Precip 10.0mm": 0.0,
      "Sunshine": 0.0,
      "Low Clouds": 0.0,
      "Mid Clouds": 0.0,
      "High Clouds": 0.0,
      "Condition": "Normal"
    },
    {
      "Datetime": "2026-07-02 23:00:00",
      "Temperature": 25.47142857142858,
      "Dewpoint": 22.514285714285716,
      "Pressure": 1012.6285714285716,
      "Rain": 0.0,
      "Wind": 5.257142857142858,
      "Wind Dir.": 94.8912016260388,
      "Wind Gust": 8.485714285714288,
      "Prob Precip 0.1mm": 8.314285714285715,
      "Prob Precip 1.0mm": 0.0,
      "Prob Precip 10.0mm": 0.0,
      "Sunshine": 0.0,
      "Low Clouds": 10.571428571428573,
      "Mid Clouds": 0.14285714285714288,
      "High Clouds": 0.0,
      "Condition": "Normal"
    },
    {
      "Datetime": "2026-07-03 00:00:00",
      "Temperature": 25.6,
      "Dewpoint": 22.7,
      "Pressure": 1012.2,
      "Rain": 0.0,
      "Wind": 8.1,
      "Wind Dir.": 99.0,
      "Wind Gust": 9.7,
      "Prob Precip 0.1mm": 6.5,
      "Prob Precip 1.0mm": 0.0,
      "Prob Precip 10.0mm": 0.0,
      "Sunshine": 0.0,
      "Low Clouds": 0.0,
      "Mid Clouds": 0.0,
      "High Clouds": 0.0,
      "Condition": "Normal"
    },
    {
      "Datetime": "2026-07-03 01:00:00",
      "Temperature": 25.5,
      "Dewpoint": 22.7,
      "Pressure": 1011.9,
      "Rain": 0.0,
      "Wind": 8.1,
      "Wind Dir.": 95.0,
      "Wind Gust": 10.8,
      "Prob Precip 0.1mm": 3.2,
      "Prob Precip 1.0mm": 0.0,
      "Prob Precip 10.0mm": 0.0,
      "Sunshine": 0.0,
      "Low Clouds": 1.0,
      "Mid Clouds": 0.0,
      "High Clouds": 0.0,
      "Condition": "Normal"
    },
    {
      "Datetime": "2026-07-03 02:00:00",
      "Temperature": 24.800000000000004,
      "Dewpoint": 22.400000000000002,
      "Pressure": 1011.8857142857145,
      "Rain": 0.0,
      "Wind": 5.714285714285714,
      "Wind Dir.": 101.42945400346636,
      "Wind Gust": 8.714285714285717,
      "Prob Precip 0.1mm": 0.0,
      "Prob Precip 1.0mm": 0.0,
      "Prob Precip 10.0mm": 0.0,
      "Sunshine": 0.0,
      "Low Clouds": 6.2857142857142865,
      "Mid Clouds": 0.14285714285714288,
      "High Clouds": 0.0,
      "Condition": "Normal"
    },
    {
      "Datetime": "2026-07-03 03:00:00",
      "Temperature": 25.4,
      "Dewpoint": 22.5,
      "Pressure": 1011.3,
      "Rain": 0.0,
      "Wind": 7.6,
      "Wind Dir.": 91.0,
      "Wind Gust": 10.3,
      "Prob Precip 0.1mm": 0.0,
      "Prob Precip 1.0mm": 0.0,
      "Prob Precip 10.0mm": 0.0,
      "Sunshine": 0.0,
      "Low Clouds": 1.0,
      "Mid Clouds": 5.0,
      "High Clouds": 0.0,
      "Condition": "Normal"
    },
    {
      "Datetime": "2026-07-03 04:00:00",
      "Temperature": 25.5,
      "Dewpoint": 22.3,
      "Pressure": 1011.3,
      "Rain": 0.0,
      "Wind": 7.0,
      "Wind Dir.": 95.0,
      "Wind Gust": 9.2,
      "Prob Precip 0.1mm": 0.0,
      "Prob Precip 1.0mm": 0.0,
      "Prob Precip 10.0mm": 0.0,
      "Sunshine": 0.0,
      "Low Clouds": 1.0,
      "Mid Clouds": 5.0,
      "High Clouds": 0.0,
      "Condition": "Normal"
    },
    {
      "Datetime": "2026-07-03 05:00:00",
      "Temperature": 24.357142857142858,
      "Dewpoint": 21.98571428571429,
      "Pressure": 1012.057142857143,
      "Rain": 0.0,
      "Wind": 4.942857142857144,
      "Wind Dir.": 97.02599561842149,
      "Wind Gust": 7.942857142857145,
      "Prob Precip 0.1mm": 0.5000000000000001,
      "Prob Precip 1.0mm": 0.0,
      "Prob Precip 10.0mm": 0.0,
      "Sunshine": 0.0,
      "Low Clouds": 0.42857142857142866,
      "Mid Clouds": 6.428571428571431,
      "High Clouds": 0.0,
      "Condition": "Normal"
    },
    {
      "Datetime": "2026-07-03 06:00:00",
      "Temperature": 25.2,
      "Dewpoint": 22.3,
      "Pressure": 1011.9,
      "Rain": 0.0,
      "Wind": 6.5,
      "Wind Dir.": 93.0,
      "Wind Gust": 8.1,
      "Prob Precip 0.1mm": 0.0,
      "Prob Precip 1.0mm": 0.0,
      "Prob Precip 10.0mm": 0.0,
      "Sunshine": 0.0,
      "Low Clouds": 3.0,
      "Mid Clouds": 82.0,
      "High Clouds": 0.0,
      "Condition": "Normal"
    },
    {
      "Datetime": "2026-07-03 07:00:00",
      "Temperature": 25.4,
      "Dewpoint": 22.1,
      "Pressure": 1012.5,
      "Rain": 0.0,
      "Wind": 5.9,
      "Wind Dir.": 92.0,
      "Wind Gust": 8.1,
      "Prob Precip 0.1mm": 0.0,
      "Prob Precip 1.0mm": 0.0,
      "Prob Precip 10.0mm": 0.0,
      "Sunshine": 28.999999999999996,
      "Low Clouds": 0.0,
      "Mid Clouds": 70.0,
      "High Clouds": 0.0,
      "Condition": "Normal"
    },
    {
      "Datetime": "2026-07-03 08:00:00",
      "Temperature": 26.27142857142858,
      "Dewpoint": 21.942857142857143,
      "Pressure": 1013.457142857143,
      "Rain": 0.0,
      "Wind": 4.314285714285715,
      "Wind Dir.": 92.43471708511585,
      "Wind Gust": 7.7857142857142865,
      "Prob Precip 0.1mm": 0.5000000000000001,
      "Prob Precip 1.0mm": 0.0,
      "Prob Precip 10.0mm": 0.0,
      "Sunshine": 21.714285714285715,
      "Low Clouds": 0.14285714285714288,
      "Mid Clouds": 1.7142857142857146,
      "High Clouds": 0.0,
      "Condition": "Normal"
    },
    {
      "Datetime": "2026-07-03 09:00:00",
      "Temperature": 27.2,
      "Dewpoint": 21.7,
      "Pressure": 1013.1,
      "Rain": 0.0,
      "Wind": 4.3,
      "Wind Dir.": 94.0,
      "Wind Gust": 7.0,
      "Prob Precip 0.1mm": 0.0,
      "Prob Precip 1.0mm": 0.0,
      "Prob Precip 10.0mm": 0.0,
      "Sunshine": 57.99999999999999,
      "Low Clouds": 0.0,
      "Mid Clouds": 5.0,
      "High Clouds": 0.0,
      "Condition": "Normal"
    },
    {
      "Datetime": "2026-07-03 10:00:00",
      "Temperature": 28.4,
      "Dewpoint": 21.0,
      "Pressure": 1012.8000000000001,
      "Rain": 0.0,
      "Wind": 2.2,
      "Wind Dir.": 84.0,
      "Wind Gust": 5.4,
      "Prob Precip 0.1mm": 0.0,
      "Prob Precip 1.0mm": 0.0,
      "Prob Precip 10.0mm": 0.0,
      "Sunshine": 59.00000000000001,
      "Low Clouds": 0.0,
      "Mid Clouds": 5.0,
      "High Clouds": 0.0,
      "Condition": "Normal"
    },
    {
      "Datetime": "2026-07-03 11:00:00",
      "Temperature": 29.742857142857144,
      "Dewpoint": 20.87142857142857,
      "Pressure": 1012.5857142857144,
      "Rain": 0.0,
      "Wind": 2.371428571428572,
      "Wind Dir.": 152.10102527345745,
      "Wind Gust": 7.857142857142858,
      "Prob Precip 0.1mm": 0.6571428571428571,
      "Prob Precip 1.0mm": 0.0,
      "Prob Precip 10.0mm": 0.0,
      "Sunshine": 30.285714285714292,
      "Low Clouds": 13.85714285714286,
      "Mid Clouds": 2.428571428571429,
      "High Clouds": 0.0,
      "Condition": "Normal"
    },
    {
      "Datetime": "2026-07-03 12:00:00",
      "Temperature": 29.300000000000004,
      "Dewpoint": 21.6,
      "Pressure": 1011.1000000000001,
      "Rain": 0.0,
      "Wind": 5.9,
      "Wind Dir.": 262.0,
      "Wind Gust": 5.4,
      "Prob Precip 0.1mm": 11.1,
      "Prob Precip 1.0mm": 0.8999999999999999,
      "Prob Precip 10.0mm": 0.0,
      "Sunshine": 49.0,
      "Low Clouds": 32.0,
      "Mid Clouds": 5.0,
      "High Clouds": 0.0,
      "Condition": "Normal"
    },
    {
      "Datetime": "2026-07-03 13:00:00",
      "Temperature": 28.7,
      "Dewpoint": 22.2,
      "Pressure": 1010.3,
      "Rain": 0.0,
      "Wind": 10.3,
      "Wind Dir.": 241.0,
      "Wind Gust": 7.6,
      "Prob Precip 0.1mm": 22.1,
      "Prob Precip 1.0mm": 1.7999999999999998,
      "Prob Precip 10.0mm": 0.0,
      "Sunshine": 32.0,
      "Low Clouds": 55.0,
      "Mid Clouds": 5.0,
      "High Clouds": 0.0,
      "Condition": "Normal"
    },
    {
      "Datetime": "2026-07-03 14:00:00",
      "Temperature": 30.028571428571436,
      "Dewpoint": 21.485714285714288,
      "Pressure": 1010.2285714285715,
      "Rain": 0.004285714285714286,
      "Wind": 6.700000000000002,
      "Wind Dir.": 241.3658528902819,
      "Wind Gust": 10.942857142857145,
      "Prob Precip 0.1mm": 33.77142857142858,
      "Prob Precip 1.0mm": 3.8285714285714287,
      "Prob Precip 10.0mm": 0.0,
      "Sunshine": 19.42857142857143,
      "Low Clouds": 44.57142857142858,
      "Mid Clouds": 11.857142857142858,
      "High Clouds": 0.0,
      "Condition": "Normal"
    },
    {
      "Datetime": "2026-07-03 15:00:00",
      "Temperature": 28.0,
      "Dewpoint": 22.9,
      "Pressure": 1009.3000000000001,
      "Rain": 0.1,
      "Wind": 9.2,
      "Wind Dir.": 217.0,
      "Wind Gust": 7.6,
      "Prob Precip 0.1mm": 50.1,
      "Prob Precip 1.0mm": 9.0,
      "Prob Precip 10.0mm": 0.0,
      "Sunshine": 7.0,
      "Low Clouds": 80.0,
      "Mid Clouds": 5.0,
      "High Clouds": 0.0,
      "Condition": "Light Rain"
    },
    {
      "Datetime": "2026-07-03 16:00:00",
      "Temperature": 28.5,
      "Dewpoint": 22.9,
      "Pressure": 1009.0999999999999,
      "Rain": 0.0,
      "Wind": 3.8,
      "Wind Dir.": 232.00000000000003,
      "Wind Gust": 3.2,
      "Prob Precip 0.1mm": 67.0,
      "Prob Precip 1.0mm": 15.2,
      "Prob Precip 10.0mm": 0.0,
      "Sunshine": 23.0,
      "Low Clouds": 38.0,
      "Mid Clouds": 5.0,
      "High Clouds": 0.0,
      "Condition": "Normal"
    },
    {
      "Datetime": "2026-07-03 17:00:00",
      "Temperature": 28.61428571428572,
      "Dewpoint": 22.485714285714288,
      "Pressure": 1010.1714285714287,
      "Rain": 0.061428571428571443,
      "Wind": 3.5428571428571436,
      "Wind Dir.": 245.50609563263896,
      "Wind Gust": 10.171428571428573,
      "Prob Precip 0.1mm": 84.52857142857144,
      "Prob Precip 1.0mm": 24.81428571428572,
      "Prob Precip 10.0mm": 0.0,
      "Sunshine": 22.000000000000004,
      "Low Clouds": 10.428571428571429,
      "Mid Clouds": 6.142857142857143,
      "High Clouds": 0.0,
      "Condition": "Normal"
    },
    {
      "Datetime": "2026-07-03 18:00:00",
      "Temperature": 27.7,
      "Dewpoint": 22.5,
      "Pressure": 1010.0,
      "Rain": 0.2,
      "Wind": 3.2,
      "Wind Dir.": 32.0,
      "Wind Gust": 6.5,
      "Prob Precip 0.1mm": 73.4,
      "Prob Precip 1.0mm": 16.8,
      "Prob Precip 10.0mm": 0.0,
      "Sunshine": 26.0,
      "Low Clouds": 11.0,
      "Mid Clouds": 78.0,
      "High Clouds": 0.0,
      "Condition": "Light Rain"
    },
    {
      "Datetime": "2026-07-03 19:00:00",
      "Temperature": 27.3,
      "Dewpoint": 22.8,
      "Pressure": 1010.6,
      "Rain": 0.1,
      "Wind": 7.0,
      "Wind Dir.": 56.0,
      "Wind Gust": 10.8,
      "Prob Precip 0.1mm": 63.0,
      "Prob Precip 1.0mm": 12.1,
      "Prob Precip 10.0mm": 0.0,
      "Sunshine": 0.0,
      "Low Clouds": 8.0,
      "Mid Clouds": 82.0,
      "High Clouds": 0.0,
      "Condition": "Light Rain"
    },
    {
      "Datetime": "2026-07-03 20:00:00",
      "Temperature": 26.38571428571429,
      "Dewpoint": 22.985714285714288,
      "Pressure": 1012.2142857142858,
      "Rain": 0.02285714285714286,
      "Wind": 4.171428571428573,
      "Wind Dir.": 91.73836685018196,
      "Wind Gust": 7.4142857142857155,
      "Prob Precip 0.1mm": 53.28571428571429,
      "Prob Precip 1.0mm": 9.3,
      "Prob Precip 10.0mm": 0.0,
      "Sunshine": 4.714285714285715,
      "Low Clouds": 9.571428571428573,
      "Mid Clouds": 3.571428571428572,
      "High Clouds": 0.0,
      "Condition": "Normal"
    },
    {
      "Datetime": "2026-07-03 23:00:00",
      "Temperature": 25.442857142857147,
      "Dewpoint": 22.6,
      "Pressure": 1013.1857142857144,
      "Rain": 0.0,
      "Wind": 5.328571428571429,
      "Wind Dir.": 89.1088683096073,
      "Wind Gust": 8.4,
      "Prob Precip 0.1mm": 4.985714285714285,
      "Prob Precip 1.0mm": 0.0,
      "Prob Precip 10.0mm": 0.0,
      "Sunshine": 0.0,
      "Low Clouds": 13.571428571428573,
      "Mid Clouds": 0.8571428571428572,
      "High Clouds": 0.0,
      "Condition": "Normal"
    },
    {
      "Datetime": "2026-07-04 02:00:00",
      "Temperature": 24.81428571428572,
      "Dewpoint": 22.5,
      "Pressure": 1012.257142857143,
      "Rain": 0.0,
      "Wind": 4.928571428571429,
      "Wind Dir.": 98.03414188169172,
      "Wind Gust": 7.942857142857144,
      "Prob Precip 0.1mm": 4.171428571428572,
      "Prob Precip 1.0mm": 0.0,
      "Prob Precip 10.0mm": 0.0,
      "Sunshine": 0.0,
      "Low Clouds": 0.7142857142857143,
      "Mid Clouds": 0.7142857142857143,
      "High Clouds": 0.0,
      "Condition": "Normal"
    },
    {
      "Datetime": "2026-07-04 05:00:00",
      "Temperature": 24.34285714285715,
      "Dewpoint": 22.371428571428574,
      "Pressure": 1012.3000000000002,
      "Rain": 0.004285714285714286,
      "Wind": 4.800000000000001,
      "Wind Dir.": 94.4545099872208,
      "Wind Gust": 7.557142857142858,
      "Prob Precip 0.1mm": 16.271428571428576,
      "Prob Precip 1.0mm": 0.0,
      "Prob Precip 10.0mm": 0.0,
      "Sunshine": 0.0,
      "Low Clouds": 2.285714285714286,
      "Mid Clouds": 14.714285714285717,
      "High Clouds": 0.0,
      "Condition": "Normal"
    },
    {
      "Datetime": "2026-07-04 08:00:00",
      "Temperature": 26.300000000000004,
      "Dewpoint": 22.485714285714288,
      "Pressure": 1013.7285714285715,
      "Rain": 0.004285714285714286,
      "Wind": 4.485714285714287,
      "Wind Dir.": 84.73117718453244,
      "Wind Gust": 8.557142857142859,
      "Prob Precip 0.1mm": 12.914285714285718,
      "Prob Precip 1.0mm": 8.571428571428573,
      "Prob Precip 10.0mm": 0.0,
      "Sunshine": 16.571428571428573,
      "Low Clouds": 7.000000000000001,
      "Mid Clouds": 9.0,
      "High Clouds": 0.0,
      "Condition": "Normal"
    },
    {
      "Datetime": "2026-07-04 11:00:00",
      "Temperature": 30.050000000000004,
      "Dewpoint": 21.85,
      "Pressure": 1012.4833333333336,
      "Rain": 0.0,
      "Wind": 3.9666666666666672,
      "Wind Dir.": 119.5006672646946,
      "Wind Gust": 9.966666666666669,
      "Prob Precip 0.1mm": 17.6,
      "Prob Precip 1.0mm": 2.5000000000000004,
      "Prob Precip 10.0mm": 0.0,
      "Sunshine": 19.666666666666668,
      "Low Clouds": 26.666666666666668,
      "Mid Clouds": 13.833333333333334,
      "High Clouds": 0.0,
      "Condition": "Normal"
    },
    {
      "Datetime": "2026-07-04 14:00:00",
      "Temperature": 29.95714285714286,
      "Dewpoint": 22.171428571428574,
      "Pressure": 1010.1571428571431,
      "Rain": 0.05571428571428572,
      "Wind": 4.485714285714287,
      "Wind Dir.": 239.1065165844518,
      "Wind Gust": 8.8,
      "Prob Precip 0.1mm": 54.228571428571435,
      "Prob Precip 1.0mm": 8.42857142857143,
      "Prob Precip 10.0mm": 0.0,
      "Sunshine": 20.000000000000004,
      "Low Clouds": 29.571428571428577,
      "Mid Clouds": 11.85714285714286,
      "High Clouds": 0.0,
      "Condition": "Normal"
    },
    {
      "Datetime": "2026-07-04 17:00:00",
      "Temperature": 28.58333333333334,
      "Dewpoint": 22.783333333333335,
      "Pressure": 1010.2666666666669,
      "Rain": 0.08333333333333334,
      "Wind": 4.5166666666666675,
      "Wind Dir.": 59.23155922178009,
      "Wind Gust": 9.550000000000002,
      "Prob Precip 0.1mm": 79.10000000000001,
      "Prob Precip 1.0mm": 23.4,
      "Prob Precip 10.0mm": 0.0,
      "Sunshine": 14.166666666666668,
      "Low Clouds": 9.166666666666668,
      "Mid Clouds": 9.666666666666668,
      "High Clouds": 0.0,
      "Condition": "Normal"
    },
    {
      "Datetime": "2026-07-04 20:00:00",
      "Temperature": 26.514285714285716,
      "Dewpoint": 22.842857142857145,
      "Pressure": 1012.3285714285716,
      "Rain": 0.03142857142857144,
      "Wind": 4.171428571428573,
      "Wind Dir.": 84.79971324538477,
      "Wind Gust": 10.271428571428574,
      "Prob Precip 0.1mm": 59.928571428571445,
      "Prob Precip 1.0mm": 0.3714285714285715,
      "Prob Precip 10.0mm": 0.0,
      "Sunshine": 10.0,
      "Low Clouds": 3.571428571428572,
      "Mid Clouds": 11.857142857142858,
      "High Clouds": 0.0,
      "Condition": "Normal"
    },
    {
      "Datetime": "2026-07-04 23:00:00",
      "Temperature": 25.940000000000005,
      "Dewpoint": 22.880000000000003,
      "Pressure": 1012.7399999999999,
      "Rain": 0.0,
      "Wind": 4.5200000000000005,
      "Wind Dir.": 93.07311815947186,
      "Wind Gust": 9.820000000000002,
      "Prob Precip 0.1mm": 8.9,
      "Prob Precip 1.0mm": 0.0,
      "Prob Precip 10.0mm": 0.0,
      "Sunshine": 0.0,
      "Low Clouds": 3.2,
      "Mid Clouds": 9.400000000000002,
      "High Clouds": 0.0,
      "Condition": "Normal"
    },
    {
      "Datetime": "2026-07-05 02:00:00",
      "Temperature": 24.942857142857154,
      "Dewpoint": 22.65714285714286,
      "Pressure": 1011.8285714285716,
      "Rain": 0.052857142857142866,
      "Wind": 5.171428571428573,
      "Wind Dir.": 104.8808880618675,
      "Wind Gust": 9.02857142857143,
      "Prob Precip 0.1mm": 2.314285714285715,
      "Prob Precip 1.0mm": 0.0,
      "Prob Precip 10.0mm": 0.0,
      "Sunshine": 0.0,
      "Low Clouds": 1.5714285714285716,
      "Mid Clouds": 17.28571428571429,
      "High Clouds": 0.0,
      "Condition": "Normal"
    },
    {
      "Datetime": "2026-07-05 05:00:00",
      "Temperature": 24.98,
      "Dewpoint": 22.520000000000003,
      "Pressure": 1012.0200000000001,
      "Rain": 0.09400000000000001,
      "Wind": 4.5200000000000005,
      "Wind Dir.": 99.49572265864433,
      "Wind Gust": 9.920000000000002,
      "Prob Precip 0.1mm": 51.50000000000001,
      "Prob Precip 1.0mm": 32.5,
      "Prob Precip 10.0mm": 0.0,
      "Sunshine": 0.0,
      "Low Clouds": 19.8,
      "Mid Clouds": 7.400000000000001,
      "High Clouds": 0.0,
      "Condition": "Normal"
    },
    {
      "Datetime": "2026-07-05 08:00:00",
      "Temperature": 26.61428571428572,
      "Dewpoint": 22.414285714285718,
      "Pressure": 1013.7000000000002,
      "Rain": 0.018571428571428576,
      "Wind": 5.342857142857144,
      "Wind Dir.": 92.89628953524141,
      "Wind Gust": 10.62857142857143,
      "Prob Precip 0.1mm": 27.85714285714286,
      "Prob Precip 1.0mm": 0.0,
      "Prob Precip 10.0mm": 0.0,
      "Sunshine": 12.285714285714288,
      "Low Clouds": 8.571428571428573,
      "Mid Clouds": 11.142857142857144,
      "High Clouds": 0.0,
      "Condition": "Normal"
    },
    {
      "Datetime": "2026-07-05 11:00:00",
      "Temperature": 30.52,
      "Dewpoint": 21.12,
      "Pressure": 1012.4400000000002,
      "Rain": 0.0,
      "Wind": 5.719999999999999,
      "Wind Dir.": 95.52901658278338,
      "Wind Gust": 13.58,
      "Prob Precip 0.1mm": 0.0,
      "Prob Precip 1.0mm": 0.0,
      "Prob Precip 10.0mm": 0.0,
      "Sunshine": 22.6,
      "Low Clouds": 13.400000000000002,
      "Mid Clouds": 16.6,
      "High Clouds": 0.0,
      "Condition": "Normal"
    },
    {
      "Datetime": "2026-07-05 14:00:00",
      "Temperature": 31.000000000000007,
      "Dewpoint": 20.814285714285717,
      "Pressure": 1010.1428571428573,
      "Rain": 0.028571428571428577,
      "Wind": 5.000000000000001,
      "Wind Dir.": 120.49042926879778,
      "Wind Gust": 10.185714285714287,
      "Prob Precip 0.1mm": 43.714285714285715,
      "Prob Precip 1.0mm": 22.65714285714286,
      "Prob Precip 10.0mm": 0.0,
      "Sunshine": 23.714285714285715,
      "Low Clouds": 17.28571428571429,
      "Mid Clouds": 10.571428571428571,
      "High Clouds": 0.0,
      "Condition": "Normal"
    },
    {
      "Datetime": "2026-07-05 17:00:00",
      "Temperature": 30.060000000000006,
      "Dewpoint": 20.48,
      "Pressure": 1010.2200000000001,
      "Rain": 0.04000000000000001,
      "Wind": 6.0600000000000005,
      "Wind Dir.": 111.7122716116906,
      "Wind Gust": 14.280000000000001,
      "Prob Precip 0.1mm": 32.9,
      "Prob Precip 1.0mm": 29.500000000000007,
      "Prob Precip 10.0mm": 0.0,
      "Sunshine": 27.000000000000004,
      "Low Clouds": 0.0,
      "Mid Clouds": 0.8,
      "High Clouds": 0.0,
      "Condition": "Normal"
    },
    {
      "Datetime": "2026-07-05 20:00:00",
      "Temperature": 26.428571428571434,
      "Dewpoint": 21.257142857142856,
      "Pressure": 1012.7285714285716,
      "Rain": 0.0,
      "Wind": 5.7857142857142865,
      "Wind Dir.": 87.33540431508916,
      "Wind Gust": 10.728571428571431,
      "Prob Precip 0.1mm": 7.571428571428571,
      "Prob Precip 1.0mm": 0.8571428571428573,
      "Prob Precip 10.0mm": 0.0,
      "Sunshine": 11.714285714285715,
      "Low Clouds": 0.0,
      "Mid Clouds": 2.0000000000000004,
      "High Clouds": 0.0,
      "Condition": "Normal"
    },
    {
      "Datetime": "2026-07-05 23:00:00",
      "Temperature": 25.62,
      "Dewpoint": 20.64,
      "Pressure": 1013.4200000000001,
      "Rain": 0.0,
      "Wind": 6.380000000000001,
      "Wind Dir.": 95.24669630405643,
      "Wind Gust": 13.82,
      "Prob Precip 0.1mm": 0.0,
      "Prob Precip 1.0mm": 0.0,
      "Prob Precip 10.0mm": 0.0,
      "Sunshine": 0.0,
      "Low Clouds": 0.0,
      "Mid Clouds": 1.0,
      "High Clouds": 0.0,
      "Condition": "Normal"
    },
    {
      "Datetime": "2026-07-06 02:00:00",
      "Temperature": 24.96666666666667,
      "Dewpoint": 21.100000000000005,
      "Pressure": 1012.6333333333334,
      "Rain": 0.0,
      "Wind": 5.850000000000001,
      "Wind Dir.": 94.78198716072819,
      "Wind Gust": 11.166666666666668,
      "Prob Precip 0.1mm": 0.0,
      "Prob Precip 1.0mm": 0.0,
      "Prob Precip 10.0mm": 0.0,
      "Sunshine": 0.0,
      "Low Clouds": 0.0,
      "Mid Clouds": 0.6666666666666667,
      "High Clouds": 0.0,
      "Condition": "Normal"
    },
    {
      "Datetime": "2026-07-06 05:00:00",
      "Temperature": 24.160000000000004,
      "Dewpoint": 20.840000000000003,
      "Pressure": 1012.8000000000002,
      "Rain": 0.0,
      "Wind": 4.420000000000001,
      "Wind Dir.": 95.99792622609228,
      "Wind Gust": 8.74,
      "Prob Precip 0.1mm": 0.0,
      "Prob Precip 1.0mm": 0.0,
      "Prob Precip 10.0mm": 0.0,
      "Sunshine": 0.0,
      "Low Clouds": 0.0,
      "Mid Clouds": 0.8,
      "High Clouds": 0.0,
      "Condition": "Normal"
    },
    {
      "Datetime": "2026-07-06 08:00:00",
      "Temperature": 26.583333333333336,
      "Dewpoint": 21.100000000000005,
      "Pressure": 1014.3833333333334,
      "Rain": 0.0,
      "Wind": 4.950000000000001,
      "Wind Dir.": 88.19982443058383,
      "Wind Gust": 11.516666666666667,
      "Prob Precip 0.1mm": 0.0,
      "Prob Precip 1.0mm": 0.0,
      "Prob Precip 10.0mm": 0.0,
      "Sunshine": 20.166666666666668,
      "Low Clouds": 0.33333333333333337,
      "Mid Clouds": 0.0,
      "High Clouds": 0.0,
      "Condition": "Normal"
    },
    {
      "Datetime": "2026-07-06 11:00:00",
      "Temperature": 29.875000000000004,
      "Dewpoint": 21.049999999999997,
      "Pressure": 1012.8749999999999,
      "Rain": 0.025,
      "Wind": 4.2,
      "Wind Dir.": 96.3250354680677,
      "Wind Gust": 11.474999999999998,
      "Prob Precip 0.1mm": 1.2,
      "Prob Precip 1.0mm": 0.0,
      "Prob Precip 10.0mm": 0.0,
      "Sunshine": 25.75,
      "Low Clouds": 7.0,
      "Mid Clouds": 0.0,
      "High Clouds": 0.0,
      "Condition": "Normal"
    },
    {
      "Datetime": "2026-07-06 14:00:00",
      "Temperature": 31.22,
      "Dewpoint": 20.32,
      "Pressure": 1010.3200000000002,
      "Rain": 0.0,
      "Wind": 4.0200000000000005,
      "Wind Dir.": 98.68298649381956,
      "Wind Gust": 11.76,
      "Prob Precip 0.1mm": 4.0,
      "Prob Precip 1.0mm": 0.0,
      "Prob Precip 10.0mm": 0.0,
      "Sunshine": 25.8,
      "Low Clouds": 17.2,
      "Mid Clouds": 7.3999999999999995,
      "High Clouds": 0.0,
      "Condition": "Normal"
    },
    {
      "Datetime": "2026-07-06 17:00:00",
      "Temperature": 29.500000000000004,
      "Dewpoint": 20.775,
      "Pressure": 1010.3750000000001,
      "Rain": 0.0,
      "Wind": 4.05,
      "Wind Dir.": 244.0786379827062,
      "Wind Gust": 10.275,
      "Prob Precip 0.1mm": 0.0,
      "Prob Precip 1.0mm": 0.0,
      "Prob Precip 10.0mm": 0.0,
      "Sunshine": 24.0,
      "Low Clouds": 0.0,
      "Mid Clouds": 0.0,
      "High Clouds": 0.0,
      "Condition": "Normal"
    },
    {
      "Datetime": "2026-07-06 20:00:00",
      "Temperature": 26.86,
      "Dewpoint": 20.400000000000002,
      "Pressure": 1012.6800000000002,
      "Rain": 0.0,
      "Wind": 5.180000000000001,
      "Wind Dir.": 85.8723457217367,
      "Wind Gust": 12.740000000000002,
      "Prob Precip 0.1mm": 6.320000000000001,
      "Prob Precip 1.0mm": 0.0,
      "Prob Precip 10.0mm": 0.0,
      "Sunshine": 10.800000000000002,
      "Low Clouds": 0.0,
      "Mid Clouds": 0.0,
      "High Clouds": 0.0,
      "Condition": "Normal"
    },
    {
      "Datetime": "2026-07-06 23:00:00",
      "Temperature": 25.375,
      "Dewpoint": 20.750000000000004,
      "Pressure": 1013.5,
      "Rain": 0.0,
      "Wind": 6.049999999999999,
      "Wind Dir.": 93.33336342205959,
      "Wind Gust": 13.775,
      "Prob Precip 0.1mm": 0.0,
      "Prob Precip 1.0mm": 0.0,
      "Prob Precip 10.0mm": 0.0,
      "Sunshine": 0.0,
      "Low Clouds": 0.0,
      "Mid Clouds": 0.0,
      "High Clouds": 0.0,
      "Condition": "Normal"
    },
    {
      "Datetime": "2026-07-07 02:00:00",
      "Temperature": 24.820000000000004,
      "Dewpoint": 21.12,
      "Pressure": 1012.54,
      "Rain": 0.0,
      "Wind": 5.9399999999999995,
      "Wind Dir.": 93.25608936693023,
      "Wind Gust": 11.56,
      "Prob Precip 0.1mm": 0.0,
      "Prob Precip 1.0mm": 0.0,
      "Prob Precip 10.0mm": 0.0,
      "Sunshine": 0.0,
      "Low Clouds": 0.0,
      "Mid Clouds": 0.0,
      "High Clouds": 0.0,
      "Condition": "Normal"
    },
    {
      "Datetime": "2026-07-07 05:00:00",
      "Temperature": 24.175,
      "Dewpoint": 20.950000000000003,
      "Pressure": 1012.75,
      "Rain": 0.0,
      "Wind": 4.975,
      "Wind Dir.": 90.667246271919,
      "Wind Gust": 9.975,
      "Prob Precip 0.1mm": 0.0,
      "Prob Precip 1.0mm": 0.0,
      "Prob Precip 10.0mm": 0.0,
      "Sunshine": 0.0,
      "Low Clouds": 1.0,
      "Mid Clouds": 0.0,
      "High Clouds": 0.0,
      "Condition": "Normal"
    },
    {
      "Datetime": "2026-07-07 08:00:00",
      "Temperature": 26.16,
      "Dewpoint": 21.26,
      "Pressure": 1014.0400000000001,
      "Rain": 0.0,
      "Wind": 4.54,
      "Wind Dir.": 99.2363770717571,
      "Wind Gust": 11.440000000000001,
      "Prob Precip 0.1mm": 0.0,
      "Prob Precip 1.0mm": 0.0,
      "Prob Precip 10.0mm": 0.0,
      "Sunshine": 16.400000000000002,
      "Low Clouds": 0.4,
      "Mid Clouds": 0.0,
      "High Clouds": 0.0,
      "Condition": "Normal"
    },
    {
      "Datetime": "2026-07-07 11:00:00",
      "Temperature": 29.8,
      "Dewpoint": 20.425,
      "Pressure": 1012.8000000000001,
      "Rain": 0.0,
      "Wind": 3.525,
      "Wind Dir.": 100.61551338234922,
      "Wind Gust": 10.25,
      "Prob Precip 0.1mm": 0.0,
      "Prob Precip 1.0mm": 0.0,
      "Prob Precip 10.0mm": 0.0,
      "Sunshine": 24.75,
      "Low Clouds": 0.75,
      "Mid Clouds": 0.0,
      "High Clouds": 0.0,
      "Condition": "Normal"
    },
    {
      "Datetime": "2026-07-07 14:00:00",
      "Temperature": 30.340000000000003,
      "Dewpoint": 21.42,
      "Pressure": 1010.0200000000002,
      "Rain": 0.006,
      "Wind": 6.580000000000001,
      "Wind Dir.": 224.2539774784885,
      "Wind Gust": 10.580000000000002,
      "Prob Precip 0.1mm": 4.640000000000001,
      "Prob Precip 1.0mm": 0.0,
      "Prob Precip 10.0mm": 0.0,
      "Sunshine": 23.999999999999996,
      "Low Clouds": 31.200000000000003,
      "Mid Clouds": 4.2,
      "High Clouds": 0.0,
      "Condition": "Normal"
    },
    {
      "Datetime": "2026-07-07 17:00:00",
      "Temperature": 29.175,
      "Dewpoint": 21.55,
      "Pressure": 1010.0500000000001,
      "Rain": 0.007499999999999999,
      "Wind": 4.05,
      "Wind Dir.": 184.44246518703812,
      "Wind Gust": 9.325,
      "Prob Precip 0.1mm": 0.5,
      "Prob Precip 1.0mm": 0.0,
      "Prob Precip 10.0mm": 0.0,
      "Sunshine": 18.0,
      "Low Clouds": 4.0,
      "Mid Clouds": 0.0,
      "High Clouds": 0.0,
      "Condition": "Normal"
    },
    {
      "Datetime": "2026-07-07 20:00:00",
      "Temperature": 26.740000000000002,
      "Dewpoint": 21.9,
      "Pressure": 1011.9000000000001,
      "Rain": 0.012,
      "Wind": 4.640000000000001,
      "Wind Dir.": 90.74303256522687,
      "Wind Gust": 12.42,
      "Prob Precip 0.1mm": 5.520000000000001,
      "Prob Precip 1.0mm": 0.0,
      "Prob Precip 10.0mm": 0.0,
      "Sunshine": 9.600000000000001,
      "Low Clouds": 3.8000000000000003,
      "Mid Clouds": 2.2,
      "High Clouds": 0.0,
      "Condition": "Normal"
    },
    {
      "Datetime": "2026-07-07 23:00:00",
      "Temperature": 25.450000000000003,
      "Dewpoint": 20.975,
      "Pressure": 1012.775,
      "Rain": 0.0,
      "Wind": 5.525,
      "Wind Dir.": 95.00030477988622,
      "Wind Gust": 12.825,
      "Prob Precip 0.1mm": 0.0,
      "Prob Precip 1.0mm": 0.0,
      "Prob Precip 10.0mm": 0.0,
      "Sunshine": 0.0,
      "Low Clouds": 0.0,
      "Mid Clouds": 0.0,
      "High Clouds": 0.0,
      "Condition": "Normal"
    },
    {
      "Datetime": "2026-07-08 02:00:00",
      "Temperature": 24.68,
      "Dewpoint": 20.92,
      "Pressure": 1011.9000000000001,
      "Rain": 0.0,
      "Wind": 5.300000000000001,
      "Wind Dir.": 97.49896953548073,
      "Wind Gust": 10.6,
      "Prob Precip 0.1mm": 0.0,
      "Prob Precip 1.0mm": 0.0,
      "Prob Precip 10.0mm": 0.0,
      "Sunshine": 0.0,
      "Low Clouds": 2.8000000000000003,
      "Mid Clouds": 0.4,
      "High Clouds": 0.0,
      "Condition": "Normal"
    },
    {
      "Datetime": "2026-07-08 05:00:00",
      "Temperature": 23.5,
      "Dewpoint": 20.3,
      "Pressure": 1012.1,
      "Rain": 0.0,
      "Wind": 6.3,
      "Wind Dir.": 91.33336342205959,
      "Wind Gust": 9.366666666666667,
      "Prob Precip 0.1mm": 0.0,
      "Prob Precip 1.0mm": 0.0,
      "Prob Precip 10.0mm": 0.0,
      "Sunshine": 0.0,
      "Low Clouds": 2.3333333333333335,
      "Mid Clouds": 0.0,
      "High Clouds": 0.0,
      "Condition": "Normal"
    },
    {
      "Datetime": "2026-07-08 08:00:00",
      "Temperature": 25.849999999999998,
      "Dewpoint": 21.0,
      "Pressure": 1013.625,
      "Rain": 0.0,
      "Wind": 5.525,
      "Wind Dir.": 94.4967942773932,
      "Wind Gust": 10.799999999999999,
      "Prob Precip 0.1mm": 0.0,
      "Prob Precip 1.0mm": 0.0,
      "Prob Precip 10.0mm": 0.0,
      "Sunshine": 11.250000000000002,
      "Low Clouds": 1.25,
      "Mid Clouds": 2.25,
      "High Clouds": 0.0,
      "Condition": "Normal"
    },
    {
      "Datetime": "2026-07-08 11:00:00",
      "Temperature": 29.5,
      "Dewpoint": 19.833333333333336,
      "Pressure": 1012.5999999999999,
      "Rain": 0.03333333333333333,
      "Wind": 4.533333333333334,
      "Wind Dir.": 110.00356237552738,
      "Wind Gust": 9.0,
      "Prob Precip 0.1mm": 0.0,
      "Prob Precip 1.0mm": 0.0,
      "Prob Precip 10.0mm": 0.0,
      "Sunshine": 15.0,
      "Low Clouds": 1.0,
      "Mid Clouds": 0.0,
      "High Clouds": 0.0,
      "Condition": "Normal"
    },
    {
      "Datetime": "2026-07-08 14:00:00",
      "Temperature": 29.974999999999998,
      "Dewpoint": 20.45,
      "Pressure": 1010.025,
      "Rain": 0.0,
      "Wind": 7.675000000000001,
      "Wind Dir.": 208.9168825886429,
      "Wind Gust": 10.799999999999999,
      "Prob Precip 0.1mm": 0.0,
      "Prob Precip 1.0mm": 0.0,
      "Prob Precip 10.0mm": 0.0,
      "Sunshine": 27.0,
      "Low Clouds": 5.25,
      "Mid Clouds": 0.0,
      "High Clouds": 0.0,
      "Condition": "Normal"
    },
    {
      "Datetime": "2026-07-08 17:00:00",
      "Temperature": 29.13333333333334,
      "Dewpoint": 20.333333333333332,
      "Pressure": 1009.9333333333334,
      "Rain": 0.0,
      "Wind": 6.1000000000000005,
      "Wind Dir.": 195.3657065861397,
      "Wind Gust": 9.000000000000002,
      "Prob Precip 0.1mm": 0.0,
      "Prob Precip 1.0mm": 0.0,
      "Prob Precip 10.0mm": 0.0,
      "Sunshine": 18.666666666666668,
      "Low Clouds": 0.6666666666666666,
      "Mid Clouds": 0.0,
      "High Clouds": 0.0,
      "Condition": "Normal"
    },
    {
      "Datetime": "2026-07-08 20:00:00",
      "Temperature": 26.325,
      "Dewpoint": 21.6,
      "Pressure": 1012.1249999999999,
      "Rain": 0.0,
      "Wind": 5.1,
      "Wind Dir.": 92.15145425046532,
      "Wind Gust": 10.825,
      "Prob Precip 0.1mm": 0.0,
      "Prob Precip 1.0mm": 0.0,
      "Prob Precip 10.0mm": 0.0,
      "Sunshine": 13.5,
      "Low Clouds": 2.0,
      "Mid Clouds": 1.5,
      "High Clouds": 0.0,
      "Condition": "Normal"
    },
    {
      "Datetime": "2026-07-09 02:00:00",
      "Temperature": 24.95,
      "Dewpoint": 22.25,
      "Pressure": 1012.2499999999999,
      "Rain": 0.0,
      "Wind": 6.2,
      "Wind Dir.": 98.49999999999999,
      "Wind Gust": 10.55,
      "Prob Precip 0.1mm": 0.0,
      "Prob Precip 1.0mm": 0.0,
      "Prob Precip 10.0mm": 0.0,
      "Sunshine": 0.0,
      "Low Clouds": 3.5,
      "Mid Clouds": 2.0,
      "High Clouds": 0.0,
      "Condition": "Normal"
    },
    {
      "Datetime": "2026-07-09 08:00:00",
      "Temperature": 25.650000000000002,
      "Dewpoint": 21.599999999999998,
      "Pressure": 1013.9,
      "Rain": 0.0,
      "Wind": 5.1,
      "Wind Dir.": 138.49999999999997,
      "Wind Gust": 10.299999999999999,
      "Prob Precip 0.1mm": 0.0,
      "Prob Precip 1.0mm": 0.0,
      "Prob Precip 10.0mm": 0.0,
      "Sunshine": 17.5,
      "Low Clouds": 0.5,
      "Mid Clouds": 0.5,
      "High Clouds": 0.0,
      "Condition": "Normal"
    },
    {
      "Datetime": "2026-07-09 14:00:00",
      "Temperature": 29.099999999999998,
      "Dewpoint": 22.200000000000003,
      "Pressure": 1010.0,
      "Rain": 0.0,
      "Wind": 7.55,
      "Wind Dir.": 190.49999999999997,
      "Wind Gust": 11.9,
      "Prob Precip 0.1mm": 0.0,
      "Prob Precip 1.0mm": 0.0,
      "Prob Precip 10.0mm": 0.0,
      "Sunshine": 53.5,
      "Low Clouds": 5.499999999999999,
      "Mid Clouds": 0.0,
      "High Clouds": 0.0,
      "Condition": "Normal"
    },
    {
      "Datetime": "2026-07-09 20:00:00",
      "Temperature": 27.0,
      "Dewpoint": 21.7,
      "Pressure": 1012.1500000000001,
      "Rain": 0.0,
      "Wind": 5.949999999999999,
      "Wind Dir.": 111.00000000000001,
      "Wind Gust": 16.45,
      "Prob Precip 0.1mm": 0.0,
      "Prob Precip 1.0mm": 0.0,
      "Prob Precip 10.0mm": 0.0,
      "Sunshine": 33.0,
      "Low Clouds": 11.5,
      "Mid Clouds": 2.0,
      "High Clouds": 0.0,
      "Condition": "Normal"
    },
    {
      "Datetime": "2026-07-10 02:00:00",
      "Temperature": 25.25,
      "Dewpoint": 22.1,
      "Pressure": 1012.1500000000001,
      "Rain": 0.0,
      "Wind": 6.2,
      "Wind Dir.": 100.0,
      "Wind Gust": 10.0,
      "Prob Precip 0.1mm": 0.0,
      "Prob Precip 1.0mm": 0.0,
      "Prob Precip 10.0mm": 0.0,
      "Sunshine": 0.0,
      "Low Clouds": 39.0,
      "Mid Clouds": 1.5,
      "High Clouds": 0.0,
      "Condition": "Normal"
    },
    {
      "Datetime": "2026-07-10 08:00:00",
      "Temperature": 26.05,
      "Dewpoint": 21.700000000000003,
      "Pressure": 1013.4499999999999,
      "Rain": 0.0,
      "Wind": 4.300000000000001,
      "Wind Dir.": 97.0,
      "Wind Gust": 7.6,
      "Prob Precip 0.1mm": 0.0,
      "Prob Precip 1.0mm": 0.0,
      "Prob Precip 10.0mm": 0.0,
      "Sunshine": 12.5,
      "Low Clouds": 2.5,
      "Mid Clouds": 0.0,
      "High Clouds": 0.0,
      "Condition": "Normal"
    },
    {
      "Datetime": "2026-07-10 14:00:00",
      "Temperature": 28.2,
      "Dewpoint": 22.95,
      "Pressure": 1009.85,
      "Rain": 0.01,
      "Wind": 9.15,
      "Wind Dir.": 241.5,
      "Wind Gust": 10.549999999999999,
      "Prob Precip 0.1mm": 0.0,
      "Prob Precip 1.0mm": 0.0,
      "Prob Precip 10.0mm": 0.0,
      "Sunshine": 44.0,
      "Low Clouds": 37.0,
      "Mid Clouds": 2.0,
      "High Clouds": 0.0,
      "Condition": "Normal"
    },
    {
      "Datetime": "2026-07-10 20:00:00",
      "Temperature": 27.0,
      "Dewpoint": 23.2,
      "Pressure": 1011.9999999999999,
      "Rain": 0.05500000000000001,
      "Wind": 8.100000000000001,
      "Wind Dir.": 65.5,
      "Wind Gust": 16.2,
      "Prob Precip 0.1mm": 0.0,
      "Prob Precip 1.0mm": 0.0,
      "Prob Precip 10.0mm": 0.0,
      "Sunshine": 28.5,
      "Low Clouds": 6.0,
      "Mid Clouds": 2.5,
      "High Clouds": 0.0,
      "Condition": "Normal"
    },
    {
      "Datetime": "2026-07-11 02:00:00",
      "Temperature": 25.4,
      "Dewpoint": 22.399999999999995,
      "Pressure": 1011.9,
      "Rain": 0.0,
      "Wind": 7.299999999999999,
      "Wind Dir.": 101.0,
      "Wind Gust": 10.5,
      "Prob Precip 0.1mm": 0.0,
      "Prob Precip 1.0mm": 0.0,
      "Prob Precip 10.0mm": 0.0,
      "Sunshine": 0.0,
      "Low Clouds": 2.5,
      "Mid Clouds": 4.0,
      "High Clouds": 0.0,
      "Condition": "Normal"
    },
    {
      "Datetime": "2026-07-11 08:00:00",
      "Temperature": 26.5,
      "Dewpoint": 22.0,
      "Pressure": 1013.7499999999999,
      "Rain": 0.0,
      "Wind": 5.65,
      "Wind Dir.": 91.5,
      "Wind Gust": 10.25,
      "Prob Precip 0.1mm": 0.0,
      "Prob Precip 1.0mm": 0.0,
      "Prob Precip 10.0mm": 0.0,
      "Sunshine": 17.5,
      "Low Clouds": 3.5,
      "Mid Clouds": 2.0,
      "High Clouds": 0.0,
      "Condition": "Normal"
    },
    {
      "Datetime": "2026-07-11 14:00:00",
      "Temperature": 29.300000000000004,
      "Dewpoint": 22.05,
      "Pressure": 1010.15,
      "Rain": 0.035,
      "Wind": 4.9,
      "Wind Dir.": 244.99999999999997,
      "Wind Gust": 7.299999999999999,
      "Prob Precip 0.1mm": 0.0,
      "Prob Precip 1.0mm": 0.0,
      "Prob Precip 10.0mm": 0.0,
      "Sunshine": 37.0,
      "Low Clouds": 49.5,
      "Mid Clouds": 9.0,
      "High Clouds": 0.0,
      "Condition": "Normal"
    },
    {
      "Datetime": "2026-07-11 20:00:00",
      "Temperature": 27.2,
      "Dewpoint": 22.100000000000005,
      "Pressure": 1012.35,
      "Rain": 0.115,
      "Wind": 10.25,
      "Wind Dir.": 83.50000000000001,
      "Wind Gust": 14.849999999999998,
      "Prob Precip 0.1mm": 0.0,
      "Prob Precip 1.0mm": 0.0,
      "Prob Precip 10.0mm": 0.0,
      "Sunshine": 23.5,
      "Low Clouds": 10.0,
      "Mid Clouds": 4.5,
      "High Clouds": 0.0,
      "Condition": "Light Rain"
    },
    {
      "Datetime": "2026-07-12 02:00:00",
      "Temperature": 25.5,
      "Dewpoint": 22.200000000000003,
      "Pressure": 1012.2500000000001,
      "Rain": 0.0,
      "Wind": 7.55,
      "Wind Dir.": 83.0,
      "Wind Gust": 12.45,
      "Prob Precip 0.1mm": 0.0,
      "Prob Precip 1.0mm": 0.0,
      "Prob Precip 10.0mm": 0.0,
      "Sunshine": 0.0,
      "Low Clouds": 4.5,
      "Mid Clouds": 7.0,
      "High Clouds": 0.0,
      "Condition": "Normal"
    },
    {
      "Datetime": "2026-07-12 08:00:00",
      "Temperature": 26.55,
      "Dewpoint": 21.5,
      "Pressure": 1013.9,
      "Rain": 0.0,
      "Wind": 7.299999999999999,
      "Wind Dir.": 91.0,
      "Wind Gust": 10.799999999999999,
      "Prob Precip 0.1mm": 0.0,
      "Prob Precip 1.0mm": 0.0,
      "Prob Precip 10.0mm": 0.0,
      "Sunshine": 17.0,
      "Low Clouds": 0.5,
      "Mid Clouds": 2.5,
      "High Clouds": 0.0,
      "Condition": "Normal"
    },
    {
      "Datetime": "2026-07-12 14:00:00",
      "Temperature": 29.699999999999996,
      "Dewpoint": 21.999999999999996,
      "Pressure": 1009.75,
      "Rain": 0.0,
      "Wind": 6.499999999999999,
      "Wind Dir.": 221.99999999999997,
      "Wind Gust": 8.600000000000001,
      "Prob Precip 0.1mm": 0.0,
      "Prob Precip 1.0mm": 0.0,
      "Prob Precip 10.0mm": 0.0,
      "Sunshine": 44.5,
      "Low Clouds": 50.0,
      "Mid Clouds": 5.499999999999999,
      "High Clouds": 0.0,
      "Condition": "Normal"
    },
    {
      "Datetime": "2026-07-12 20:00:00",
      "Temperature": 27.15,
      "Dewpoint": 21.599999999999998,
      "Pressure": 1012.2500000000001,
      "Rain": 0.16,
      "Wind": 8.4,
      "Wind Dir.": 87.00000000000001,
      "Wind Gust": 17.0,
      "Prob Precip 0.1mm": 0.0,
      "Prob Precip 1.0mm": 0.0,
      "Prob Precip 10.0mm": 0.0,
      "Sunshine": 24.5,
      "Low Clouds": 11.5,
      "Mid Clouds": 19.5,
      "High Clouds": 0.0,
      "Condition": "Light Rain"
    },
    {
      "Datetime": "2026-07-13 02:00:00",
      "Temperature": 25.55,
      "Dewpoint": 21.45,
      "Pressure": 1011.8500000000001,
      "Rain": 0.0,
      "Wind": 5.8999999999999995,
      "Wind Dir.": 91.50000000000001,
      "Wind Gust": 11.6,
      "Prob Precip 0.1mm": 0.0,
      "Prob Precip 1.0mm": 0.0,
      "Prob Precip 10.0mm": 0.0,
      "Sunshine": 0.0,
      "Low Clouds": 3.5,
      "Mid Clouds": 31.5,
      "High Clouds": 0.0,
      "Condition": "Normal"
    },
    {
      "Datetime": "2026-07-13 08:00:00",
      "Temperature": 26.45,
      "Dewpoint": 21.2,
      "Pressure": 1013.25,
      "Rain": 0.0,
      "Wind": 5.949999999999999,
      "Wind Dir.": 88.5,
      "Wind Gust": 9.450000000000001,
      "Prob Precip 0.1mm": 0.0,
      "Prob Precip 1.0mm": 0.0,
      "Prob Precip 10.0mm": 0.0,
      "Sunshine": 15.500000000000002,
      "Low Clouds": 3.5,
      "Mid Clouds": 15.0,
      "High Clouds": 0.0,
      "Condition": "Normal"
    },
    {
      "Datetime": "2026-07-13 14:00:00",
      "Temperature": 29.900000000000002,
      "Dewpoint": 22.2,
      "Pressure": 1007.8,
      "Rain": 0.0,
      "Wind": 2.7,
      "Wind Dir.": 164.0,
      "Wind Gust": 6.5,
      "Prob Precip 0.1mm": 0.0,
      "Prob Precip 1.0mm": 0.0,
      "Prob Precip 10.0mm": 0.0,
      "Sunshine": 19.0,
      "Low Clouds": 100.0,
      "Mid Clouds": 5.0,
      "High Clouds": 0.0,
      "Condition": "Normal"
    },
    {
      "Datetime": "2026-07-13 20:00:00",
      "Temperature": 27.0,
      "Dewpoint": 21.6,
      "Pressure": 1010.4,
      "Rain": 0.13,
      "Wind": 8.6,
      "Wind Dir.": 77.0,
      "Wind Gust": 14.599999999999998,
      "Prob Precip 0.1mm": 0.0,
      "Prob Precip 1.0mm": 0.0,
      "Prob Precip 10.0mm": 0.0,
      "Sunshine": 17.0,
      "Low Clouds": 15.0,
      "Mid Clouds": 0.0,
      "High Clouds": 0.0,
      "Condition": "Light Rain"
    },
    {
      "Datetime": "2026-07-14 02:00:00",
      "Temperature": 25.1,
      "Dewpoint": 22.2,
      "Pressure": 1009.9000000000001,
      "Rain": 0.0,
      "Wind": 8.1,
      "Wind Dir.": 99.0,
      "Wind Gust": 11.9,
      "Prob Precip 0.1mm": 0.0,
      "Prob Precip 1.0mm": 0.0,
      "Prob Precip 10.0mm": 0.0,
      "Sunshine": 0.0,
      "Low Clouds": 1.0,
      "Mid Clouds": 0.0,
      "High Clouds": 0.0,
      "Condition": "Normal"
    },
    {
      "Datetime": "2026-07-14 08:00:00",
      "Temperature": 26.4,
      "Dewpoint": 21.7,
      "Pressure": 1012.3999999999999,
      "Rain": 0.0,
      "Wind": 7.0,
      "Wind Dir.": 94.0,
      "Wind Gust": 10.3,
      "Prob Precip 0.1mm": 0.0,
      "Prob Precip 1.0mm": 0.0,
      "Prob Precip 10.0mm": 0.0,
      "Sunshine": 19.0,
      "Low Clouds": 0.0,
      "Mid Clouds": 0.0,
      "High Clouds": 0.0,
      "Condition": "Normal"
    },
    {
      "Datetime": "2026-07-14 14:00:00",
      "Temperature": 29.500000000000004,
      "Dewpoint": 21.4,
      "Pressure": 1008.4,
      "Rain": 0.0,
      "Wind": 4.9,
      "Wind Dir.": 268.0,
      "Wind Gust": 4.3,
      "Prob Precip 0.1mm": 0.0,
      "Prob Precip 1.0mm": 0.0,
      "Prob Precip 10.0mm": 0.0,
      "Sunshine": 30.0,
      "Low Clouds": 100.0,
      "Mid Clouds": 0.0,
      "High Clouds": 0.0,
      "Condition": "Normal"
    },
    {
      "Datetime": "2026-07-14 20:00:00",
      "Temperature": 27.2,
      "Dewpoint": 21.4,
      "Pressure": 1010.6,
      "Rain": 0.05,
      "Wind": 9.2,
      "Wind Dir.": 76.0,
      "Wind Gust": 11.9,
      "Prob Precip 0.1mm": 0.0,
      "Prob Precip 1.0mm": 0.0,
      "Prob Precip 10.0mm": 0.0,
      "Sunshine": 15.0,
      "Low Clouds": 4.0,
      "Mid Clouds": 0.0,
      "High Clouds": 0.0,
      "Condition": "Normal"
    }
  ]
}